{
  "export_time": "2025-09-01T21:26:21.841489",
  "log_count": 250,
  "logs": [
    {
      "timestamp": "2025-09-01T21:26:13.833717",
      "level": "INFO",
      "message": "线程0日志0",
      "module": "thread_0",
      "function": "",
      "line": 0,
      "thread_id": "315012",
      "task_id": null,
      "user_id": null,
      "context": null,
      "exception": null
    },
    {
      "timestamp": "2025-09-01T21:26:13.833950",
      "level": "INFO",
      "message": "线程1日志0",
      "module": "thread_1",
      "function": "",
      "line": 0,
      "thread_id": "51932",
      "task_id": null,
      "user_id": null,
      "context": null,
      "exception": null
    },
    {
      "timestamp": "2025-09-01T21:26:13.834143",
      "level": "INFO",
      "message": "线程2日志0",
      "module": "thread_2",
      "function": "",
      "line": 0,
      "thread_id": "19368",
      "task_id": null,
      "user_id": null,
      "context": null,
      "exception": null
    },
    {
      "timestamp": "2025-09-01T21:26:13.834317",
      "level": "INFO",
      "message": "线程3日志0",
      "module": "thread_3",
      "function": "",
      "line": 0,
      "thread_id": "19856",
      "task_id": null,
      "user_id": null,
      "context": null,
      "exception": null
    },
    {
      "timestamp": "2025-09-01T21:26:13.834472",
      "level": "INFO",
      "message": "线程4日志0",
      "module": "thread_4",
      "function": "",
      "line": 0,
      "thread_id": "283448",
      "task_id": null,
      "user_id": null,
      "context": null,
      "exception": null
    },
    {
      "timestamp": "2025-09-01T21:26:13.835113",
      "level": "INFO",
      "message": "线程1日志1",
      "module": "thread_1",
      "function": "",
      "line": 0,
      "thread_id": "51932",
      "task_id": null,
      "user_id": null,
      "context": null,
      "exception": null
    },
    {
      "timestamp": "2025-09-01T21:26:13.835306",
      "level": "INFO",
      "message": "线程0日志1",
      "module": "thread_0",
      "function": "",
      "line": 0,
      "thread_id": "315012",
      "task_id": null,
      "user_id": null,
      "context": null,
      "exception": null
    },
    {
      "timestamp": "2025-09-01T21:26:13.835455",
      "level": "INFO",
      "message": "线程3日志1",
      "module": "thread_3",
      "function": "",
      "line": 0,
      "thread_id": "19856",
      "task_id": null,
      "user_id": null,
      "context": null,
      "exception": null
    },
    {
      "timestamp": "2025-09-01T21:26:13.835688",
      "level": "INFO",
      "message": "线程4日志1",
      "module": "thread_4",
      "function": "",
      "line": 0,
      "thread_id": "283448",
      "task_id": null,
      "user_id": null,
      "context": null,
      "exception": null
    },
    {
      "timestamp": "2025-09-01T21:26:13.835834",
      "level": "INFO",
      "message": "线程2日志1",
      "module": "thread_2",
      "function": "",
      "line": 0,
      "thread_id": "19368",
      "task_id": null,
      "user_id": null,
      "context": null,
      "exception": null
    },
    {
      "timestamp": "2025-09-01T21:26:13.836058",
      "level": "INFO",
      "message": "线程1日志2",
      "module": "thread_1",
      "function": "",
      "line": 0,
      "thread_id": "51932",
      "task_id": null,
      "user_id": null,
      "context": null,
      "exception": null
    },
    {
      "timestamp": "2025-09-01T21:26:13.836304",
      "level": "INFO",
      "message": "线程3日志2",
      "module": "thread_3",
      "function": "",
      "line": 0,
      "thread_id": "19856",
      "task_id": null,
      "user_id": null,
      "context": null,
      "exception": null
    },
    {
      "timestamp": "2025-09-01T21:26:13.836576",
      "level": "INFO",
      "message": "线程4日志2",
      "module": "thread_4",
      "function": "",
      "line": 0,
      "thread_id": "283448",
      "task_id": null,
      "user_id": null,
      "context": null,
      "exception": null
    },
    {
      "timestamp": "2025-09-01T21:26:13.836815",
      "level": "INFO",
      "message": "线程3日志3",
      "module": "thread_3",
      "function": "",
      "line": 0,
      "thread_id": "19856",
      "task_id": null,
      "user_id": null,
      "context": null,
      "exception": null
    },
    {
      "timestamp": "2025-09-01T21:26:13.836979",
      "level": "INFO",
      "message": "线程1日志3",
      "module": "thread_1",
      "function": "",
      "line": 0,
      "thread_id": "51932",
      "task_id": null,
      "user_id": null,
      "context": null,
      "exception": null
    },
    {
      "timestamp": "2025-09-01T21:26:13.837158",
      "level": "INFO",
      "message": "线程2日志2",
      "module": "thread_2",
      "function": "",
      "line": 0,
      "thread_id": "19368",
      "task_id": null,
      "user_id": null,
      "context": null,
      "exception": null
    },
    {
      "timestamp": "2025-09-01T21:26:13.837228",
      "level": "INFO",
      "message": "线程0日志2",
      "module": "thread_0",
      "function": "",
      "line": 0,
      "thread_id": "315012",
      "task_id": null,
      "user_id": null,
      "context": null,
      "exception": null
    },
    {
      "timestamp": "2025-09-01T21:26:13.837386",
      "level": "INFO",
      "message": "线程4日志3",
      "module": "thread_4",
      "function": "",
      "line": 0,
      "thread_id": "283448",
      "task_id": null,
      "user_id": null,
      "context": null,
      "exception": null
    },
    {
      "timestamp": "2025-09-01T21:26:13.837471",
      "level": "INFO",
      "message": "线程3日志4",
      "module": "thread_3",
      "function": "",
      "line": 0,
      "thread_id": "19856",
      "task_id": null,
      "user_id": null,
      "context": null,
      "exception": null
    },
    {
      "timestamp": "2025-09-01T21:26:13.837955",
      "level": "INFO",
      "message": "线程4日志4",
      "module": "thread_4",
      "function": "",
      "line": 0,
      "thread_id": "283448",
      "task_id": null,
      "user_id": null,
      "context": null,
      "exception": null
    },
    {
      "timestamp": "2025-09-01T21:26:13.838097",
      "level": "INFO",
      "message": "线程0日志3",
      "module": "thread_0",
      "function": "",
      "line": 0,
      "thread_id": "315012",
      "task_id": null,
      "user_id": null,
      "context": null,
      "exception": null
    },
    {
      "timestamp": "2025-09-01T21:26:13.838173",
      "level": "INFO",
      "message": "线程1日志4",
      "module": "thread_1",
      "function": "",
      "line": 0,
      "thread_id": "51932",
      "task_id": null,
      "user_id": null,
      "context": null,
      "exception": null
    },
    {
      "timestamp": "2025-09-01T21:26:13.838256",
      "level": "INFO",
      "message": "线程3日志5",
      "module": "thread_3",
      "function": "",
      "line": 0,
      "thread_id": "19856",
      "task_id": null,
      "user_id": null,
      "context": null,
      "exception": null
    },
    {
      "timestamp": "2025-09-01T21:26:13.838682",
      "level": "INFO",
      "message": "线程4日志5",
      "module": "thread_4",
      "function": "",
      "line": 0,
      "thread_id": "283448",
      "task_id": null,
      "user_id": null,
      "context": null,
      "exception": null
    },
    {
      "timestamp": "2025-09-01T21:26:13.838850",
      "level": "INFO",
      "message": "线程2日志3",
      "module": "thread_2",
      "function": "",
      "line": 0,
      "thread_id": "19368",
      "task_id": null,
      "user_id": null,
      "context": null,
      "exception": null
    },
    {
      "timestamp": "2025-09-01T21:26:13.838989",
      "level": "INFO",
      "message": "线程1日志5",
      "module": "thread_1",
      "function": "",
      "line": 0,
      "thread_id": "51932",
      "task_id": null,
      "user_id": null,
      "context": null,
      "exception": null
    },
    {
      "timestamp": "2025-09-01T21:26:13.839060",
      "level": "INFO",
      "message": "线程0日志4",
      "module": "thread_0",
      "function": "",
      "line": 0,
      "thread_id": "315012",
      "task_id": null,
      "user_id": null,
      "context": null,
      "exception": null
    },
    {
      "timestamp": "2025-09-01T21:26:13.839221",
      "level": "INFO",
      "message": "线程3日志6",
      "module": "thread_3",
      "function": "",
      "line": 0,
      "thread_id": "19856",
      "task_id": null,
      "user_id": null,
      "context": null,
      "exception": null
    },
    {
      "timestamp": "2025-09-01T21:26:13.839439",
      "level": "INFO",
      "message": "线程0日志5",
      "module": "thread_0",
      "function": "",
      "line": 0,
      "thread_id": "315012",
      "task_id": null,
      "user_id": null,
      "context": null,
      "exception": null
    },
    {
      "timestamp": "2025-09-01T21:26:13.839556",
      "level": "INFO",
      "message": "线程1日志6",
      "module": "thread_1",
      "function": "",
      "line": 0,
      "thread_id": "51932",
      "task_id": null,
      "user_id": null,
      "context": null,
      "exception": null
    },
    {
      "timestamp": "2025-09-01T21:26:13.839788",
      "level": "INFO",
      "message": "线程3日志7",
      "module": "thread_3",
      "function": "",
      "line": 0,
      "thread_id": "19856",
      "task_id": null,
      "user_id": null,
      "context": null,
      "exception": null
    },
    {
      "timestamp": "2025-09-01T21:26:13.839955",
      "level": "INFO",
      "message": "线程2日志4",
      "module": "thread_2",
      "function": "",
      "line": 0,
      "thread_id": "19368",
      "task_id": null,
      "user_id": null,
      "context": null,
      "exception": null
    },
    {
      "timestamp": "2025-09-01T21:26:13.840150",
      "level": "INFO",
      "message": "线程4日志6",
      "module": "thread_4",
      "function": "",
      "line": 0,
      "thread_id": "283448",
      "task_id": null,
      "user_id": null,
      "context": null,
      "exception": null
    },
    {
      "timestamp": "2025-09-01T21:26:13.840339",
      "level": "INFO",
      "message": "线程0日志6",
      "module": "thread_0",
      "function": "",
      "line": 0,
      "thread_id": "315012",
      "task_id": null,
      "user_id": null,
      "context": null,
      "exception": null
    },
    {
      "timestamp": "2025-09-01T21:26:13.840508",
      "level": "INFO",
      "message": "线程1日志7",
      "module": "thread_1",
      "function": "",
      "line": 0,
      "thread_id": "51932",
      "task_id": null,
      "user_id": null,
      "context": null,
      "exception": null
    },
    {
      "timestamp": "2025-09-01T21:26:13.841161",
      "level": "INFO",
      "message": "线程2日志5",
      "module": "thread_2",
      "function": "",
      "line": 0,
      "thread_id": "19368",
      "task_id": null,
      "user_id": null,
      "context": null,
      "exception": null
    },
    {
      "timestamp": "2025-09-01T21:26:13.841265",
      "level": "INFO",
      "message": "线程3日志8",
      "module": "thread_3",
      "function": "",
      "line": 0,
      "thread_id": "19856",
      "task_id": null,
      "user_id": null,
      "context": null,
      "exception": null
    },
    {
      "timestamp": "2025-09-01T21:26:13.841410",
      "level": "INFO",
      "message": "线程1日志8",
      "module": "thread_1",
      "function": "",
      "line": 0,
      "thread_id": "51932",
      "task_id": null,
      "user_id": null,
      "context": null,
      "exception": null
    },
    {
      "timestamp": "2025-09-01T21:26:13.841513",
      "level": "INFO",
      "message": "线程0日志7",
      "module": "thread_0",
      "function": "",
      "line": 0,
      "thread_id": "315012",
      "task_id": null,
      "user_id": null,
      "context": null,
      "exception": null
    },
    {
      "timestamp": "2025-09-01T21:26:13.841585",
      "level": "INFO",
      "message": "线程4日志7",
      "module": "thread_4",
      "function": "",
      "line": 0,
      "thread_id": "283448",
      "task_id": null,
      "user_id": null,
      "context": null,
      "exception": null
    },
    {
      "timestamp": "2025-09-01T21:26:13.841754",
      "level": "INFO",
      "message": "线程2日志6",
      "module": "thread_2",
      "function": "",
      "line": 0,
      "thread_id": "19368",
      "task_id": null,
      "user_id": null,
      "context": null,
      "exception": null
    },
    {
      "timestamp": "2025-09-01T21:26:13.841987",
      "level": "INFO",
      "message": "线程1日志9",
      "module": "thread_1",
      "function": "",
      "line": 0,
      "thread_id": "51932",
      "task_id": null,
      "user_id": null,
      "context": null,
      "exception": null
    },
    {
      "timestamp": "2025-09-01T21:26:13.842153",
      "level": "INFO",
      "message": "线程3日志9",
      "module": "thread_3",
      "function": "",
      "line": 0,
      "thread_id": "19856",
      "task_id": null,
      "user_id": null,
      "context": null,
      "exception": null
    },
    {
      "timestamp": "2025-09-01T21:26:13.842282",
      "level": "INFO",
      "message": "线程4日志8",
      "module": "thread_4",
      "function": "",
      "line": 0,
      "thread_id": "283448",
      "task_id": null,
      "user_id": null,
      "context": null,
      "exception": null
    },
    {
      "timestamp": "2025-09-01T21:26:13.842477",
      "level": "INFO",
      "message": "线程0日志8",
      "module": "thread_0",
      "function": "",
      "line": 0,
      "thread_id": "315012",
      "task_id": null,
      "user_id": null,
      "context": null,
      "exception": null
    },
    {
      "timestamp": "2025-09-01T21:26:13.842736",
      "level": "INFO",
      "message": "线程1日志10",
      "module": "thread_1",
      "function": "",
      "line": 0,
      "thread_id": "51932",
      "task_id": null,
      "user_id": null,
      "context": null,
      "exception": null
    },
    {
      "timestamp": "2025-09-01T21:26:13.842875",
      "level": "INFO",
      "message": "线程2日志7",
      "module": "thread_2",
      "function": "",
      "line": 0,
      "thread_id": "19368",
      "task_id": null,
      "user_id": null,
      "context": null,
      "exception": null
    },
    {
      "timestamp": "2025-09-01T21:26:13.843041",
      "level": "INFO",
      "message": "线程4日志9",
      "module": "thread_4",
      "function": "",
      "line": 0,
      "thread_id": "283448",
      "task_id": null,
      "user_id": null,
      "context": null,
      "exception": null
    },
    {
      "timestamp": "2025-09-01T21:26:13.843121",
      "level": "INFO",
      "message": "线程3日志10",
      "module": "thread_3",
      "function": "",
      "line": 0,
      "thread_id": "19856",
      "task_id": null,
      "user_id": null,
      "context": null,
      "exception": null
    },
    {
      "timestamp": "2025-09-01T21:26:13.843334",
      "level": "INFO",
      "message": "线程0日志9",
      "module": "thread_0",
      "function": "",
      "line": 0,
      "thread_id": "315012",
      "task_id": null,
      "user_id": null,
      "context": null,
      "exception": null
    },
    {
      "timestamp": "2025-09-01T21:26:13.843470",
      "level": "INFO",
      "message": "线程2日志8",
      "module": "thread_2",
      "function": "",
      "line": 0,
      "thread_id": "19368",
      "task_id": null,
      "user_id": null,
      "context": null,
      "exception": null
    },
    {
      "timestamp": "2025-09-01T21:26:13.843634",
      "level": "INFO",
      "message": "线程1日志11",
      "module": "thread_1",
      "function": "",
      "line": 0,
      "thread_id": "51932",
      "task_id": null,
      "user_id": null,
      "context": null,
      "exception": null
    },
    {
      "timestamp": "2025-09-01T21:26:13.843814",
      "level": "INFO",
      "message": "线程3日志11",
      "module": "thread_3",
      "function": "",
      "line": 0,
      "thread_id": "19856",
      "task_id": null,
      "user_id": null,
      "context": null,
      "exception": null
    },
    {
      "timestamp": "2025-09-01T21:26:13.843947",
      "level": "INFO",
      "message": "线程4日志10",
      "module": "thread_4",
      "function": "",
      "line": 0,
      "thread_id": "283448",
      "task_id": null,
      "user_id": null,
      "context": null,
      "exception": null
    },
    {
      "timestamp": "2025-09-01T21:26:13.844371",
      "level": "INFO",
      "message": "线程1日志12",
      "module": "thread_1",
      "function": "",
      "line": 0,
      "thread_id": "51932",
      "task_id": null,
      "user_id": null,
      "context": null,
      "exception": null
    },
    {
      "timestamp": "2025-09-01T21:26:13.844513",
      "level": "INFO",
      "message": "线程2日志9",
      "module": "thread_2",
      "function": "",
      "line": 0,
      "thread_id": "19368",
      "task_id": null,
      "user_id": null,
      "context": null,
      "exception": null
    },
    {
      "timestamp": "2025-09-01T21:26:13.844568",
      "level": "INFO",
      "message": "线程3日志12",
      "module": "thread_3",
      "function": "",
      "line": 0,
      "thread_id": "19856",
      "task_id": null,
      "user_id": null,
      "context": null,
      "exception": null
    },
    {
      "timestamp": "2025-09-01T21:26:13.844652",
      "level": "INFO",
      "message": "线程0日志10",
      "module": "thread_0",
      "function": "",
      "line": 0,
      "thread_id": "315012",
      "task_id": null,
      "user_id": null,
      "context": null,
      "exception": null
    },
    {
      "timestamp": "2025-09-01T21:26:13.844733",
      "level": "INFO",
      "message": "线程4日志11",
      "module": "thread_4",
      "function": "",
      "line": 0,
      "thread_id": "283448",
      "task_id": null,
      "user_id": null,
      "context": null,
      "exception": null
    },
    {
      "timestamp": "2025-09-01T21:26:13.844875",
      "level": "INFO",
      "message": "线程1日志13",
      "module": "thread_1",
      "function": "",
      "line": 0,
      "thread_id": "51932",
      "task_id": null,
      "user_id": null,
      "context": null,
      "exception": null
    },
    {
      "timestamp": "2025-09-01T21:26:13.845119",
      "level": "INFO",
      "message": "线程3日志13",
      "module": "thread_3",
      "function": "",
      "line": 0,
      "thread_id": "19856",
      "task_id": null,
      "user_id": null,
      "context": null,
      "exception": null
    },
    {
      "timestamp": "2025-09-01T21:26:13.845265",
      "level": "INFO",
      "message": "线程2日志10",
      "module": "thread_2",
      "function": "",
      "line": 0,
      "thread_id": "19368",
      "task_id": null,
      "user_id": null,
      "context": null,
      "exception": null
    },
    {
      "timestamp": "2025-09-01T21:26:13.845358",
      "level": "INFO",
      "message": "线程0日志11",
      "module": "thread_0",
      "function": "",
      "line": 0,
      "thread_id": "315012",
      "task_id": null,
      "user_id": null,
      "context": null,
      "exception": null
    },
    {
      "timestamp": "2025-09-01T21:26:13.845556",
      "level": "INFO",
      "message": "线程4日志12",
      "module": "thread_4",
      "function": "",
      "line": 0,
      "thread_id": "283448",
      "task_id": null,
      "user_id": null,
      "context": null,
      "exception": null
    },
    {
      "timestamp": "2025-09-01T21:26:13.845647",
      "level": "INFO",
      "message": "线程1日志14",
      "module": "thread_1",
      "function": "",
      "line": 0,
      "thread_id": "51932",
      "task_id": null,
      "user_id": null,
      "context": null,
      "exception": null
    },
    {
      "timestamp": "2025-09-01T21:26:13.845775",
      "level": "INFO",
      "message": "线程3日志14",
      "module": "thread_3",
      "function": "",
      "line": 0,
      "thread_id": "19856",
      "task_id": null,
      "user_id": null,
      "context": null,
      "exception": null
    },
    {
      "timestamp": "2025-09-01T21:26:13.845956",
      "level": "INFO",
      "message": "线程2日志11",
      "module": "thread_2",
      "function": "",
      "line": 0,
      "thread_id": "19368",
      "task_id": null,
      "user_id": null,
      "context": null,
      "exception": null
    },
    {
      "timestamp": "2025-09-01T21:26:13.846093",
      "level": "INFO",
      "message": "线程0日志12",
      "module": "thread_0",
      "function": "",
      "line": 0,
      "thread_id": "315012",
      "task_id": null,
      "user_id": null,
      "context": null,
      "exception": null
    },
    {
      "timestamp": "2025-09-01T21:26:13.846239",
      "level": "INFO",
      "message": "线程4日志13",
      "module": "thread_4",
      "function": "",
      "line": 0,
      "thread_id": "283448",
      "task_id": null,
      "user_id": null,
      "context": null,
      "exception": null
    },
    {
      "timestamp": "2025-09-01T21:26:13.846362",
      "level": "INFO",
      "message": "线程1日志15",
      "module": "thread_1",
      "function": "",
      "line": 0,
      "thread_id": "51932",
      "task_id": null,
      "user_id": null,
      "context": null,
      "exception": null
    },
    {
      "timestamp": "2025-09-01T21:26:13.846563",
      "level": "INFO",
      "message": "线程3日志15",
      "module": "thread_3",
      "function": "",
      "line": 0,
      "thread_id": "19856",
      "task_id": null,
      "user_id": null,
      "context": null,
      "exception": null
    },
    {
      "timestamp": "2025-09-01T21:26:13.846642",
      "level": "INFO",
      "message": "线程2日志12",
      "module": "thread_2",
      "function": "",
      "line": 0,
      "thread_id": "19368",
      "task_id": null,
      "user_id": null,
      "context": null,
      "exception": null
    },
    {
      "timestamp": "2025-09-01T21:26:13.846785",
      "level": "INFO",
      "message": "线程0日志13",
      "module": "thread_0",
      "function": "",
      "line": 0,
      "thread_id": "315012",
      "task_id": null,
      "user_id": null,
      "context": null,
      "exception": null
    },
    {
      "timestamp": "2025-09-01T21:26:13.846938",
      "level": "INFO",
      "message": "线程1日志16",
      "module": "thread_1",
      "function": "",
      "line": 0,
      "thread_id": "51932",
      "task_id": null,
      "user_id": null,
      "context": null,
      "exception": null
    },
    {
      "timestamp": "2025-09-01T21:26:13.847046",
      "level": "INFO",
      "message": "线程3日志16",
      "module": "thread_3",
      "function": "",
      "line": 0,
      "thread_id": "19856",
      "task_id": null,
      "user_id": null,
      "context": null,
      "exception": null
    },
    {
      "timestamp": "2025-09-01T21:26:13.847171",
      "level": "INFO",
      "message": "线程4日志14",
      "module": "thread_4",
      "function": "",
      "line": 0,
      "thread_id": "283448",
      "task_id": null,
      "user_id": null,
      "context": null,
      "exception": null
    },
    {
      "timestamp": "2025-09-01T21:26:13.847409",
      "level": "INFO",
      "message": "线程2日志13",
      "module": "thread_2",
      "function": "",
      "line": 0,
      "thread_id": "19368",
      "task_id": null,
      "user_id": null,
      "context": null,
      "exception": null
    },
    {
      "timestamp": "2025-09-01T21:26:13.847486",
      "level": "INFO",
      "message": "线程3日志17",
      "module": "thread_3",
      "function": "",
      "line": 0,
      "thread_id": "19856",
      "task_id": null,
      "user_id": null,
      "context": null,
      "exception": null
    },
    {
      "timestamp": "2025-09-01T21:26:13.847611",
      "level": "INFO",
      "message": "线程0日志14",
      "module": "thread_0",
      "function": "",
      "line": 0,
      "thread_id": "315012",
      "task_id": null,
      "user_id": null,
      "context": null,
      "exception": null
    },
    {
      "timestamp": "2025-09-01T21:26:13.847780",
      "level": "INFO",
      "message": "线程1日志17",
      "module": "thread_1",
      "function": "",
      "line": 0,
      "thread_id": "51932",
      "task_id": null,
      "user_id": null,
      "context": null,
      "exception": null
    },
    {
      "timestamp": "2025-09-01T21:26:13.847909",
      "level": "INFO",
      "message": "线程2日志14",
      "module": "thread_2",
      "function": "",
      "line": 0,
      "thread_id": "19368",
      "task_id": null,
      "user_id": null,
      "context": null,
      "exception": null
    },
    {
      "timestamp": "2025-09-01T21:26:13.848171",
      "level": "INFO",
      "message": "线程4日志15",
      "module": "thread_4",
      "function": "",
      "line": 0,
      "thread_id": "283448",
      "task_id": null,
      "user_id": null,
      "context": null,
      "exception": null
    },
    {
      "timestamp": "2025-09-01T21:26:13.848284",
      "level": "INFO",
      "message": "线程1日志18",
      "module": "thread_1",
      "function": "",
      "line": 0,
      "thread_id": "51932",
      "task_id": null,
      "user_id": null,
      "context": null,
      "exception": null
    },
    {
      "timestamp": "2025-09-01T21:26:13.848361",
      "level": "INFO",
      "message": "线程0日志15",
      "module": "thread_0",
      "function": "",
      "line": 0,
      "thread_id": "315012",
      "task_id": null,
      "user_id": null,
      "context": null,
      "exception": null
    },
    {
      "timestamp": "2025-09-01T21:26:13.848487",
      "level": "INFO",
      "message": "线程3日志18",
      "module": "thread_3",
      "function": "",
      "line": 0,
      "thread_id": "19856",
      "task_id": null,
      "user_id": null,
      "context": null,
      "exception": null
    },
    {
      "timestamp": "2025-09-01T21:26:13.848635",
      "level": "INFO",
      "message": "线程2日志15",
      "module": "thread_2",
      "function": "",
      "line": 0,
      "thread_id": "19368",
      "task_id": null,
      "user_id": null,
      "context": null,
      "exception": null
    },
    {
      "timestamp": "2025-09-01T21:26:13.848799",
      "level": "INFO",
      "message": "线程4日志16",
      "module": "thread_4",
      "function": "",
      "line": 0,
      "thread_id": "283448",
      "task_id": null,
      "user_id": null,
      "context": null,
      "exception": null
    },
    {
      "timestamp": "2025-09-01T21:26:13.849081",
      "level": "INFO",
      "message": "线程0日志16",
      "module": "thread_0",
      "function": "",
      "line": 0,
      "thread_id": "315012",
      "task_id": null,
      "user_id": null,
      "context": null,
      "exception": null
    },
    {
      "timestamp": "2025-09-01T21:26:13.849167",
      "level": "INFO",
      "message": "线程2日志16",
      "module": "thread_2",
      "function": "",
      "line": 0,
      "thread_id": "19368",
      "task_id": null,
      "user_id": null,
      "context": null,
      "exception": null
    },
    {
      "timestamp": "2025-09-01T21:26:13.849278",
      "level": "INFO",
      "message": "线程1日志19",
      "module": "thread_1",
      "function": "",
      "line": 0,
      "thread_id": "51932",
      "task_id": null,
      "user_id": null,
      "context": null,
      "exception": null
    },
    {
      "timestamp": "2025-09-01T21:26:13.849403",
      "level": "INFO",
      "message": "线程4日志17",
      "module": "thread_4",
      "function": "",
      "line": 0,
      "thread_id": "283448",
      "task_id": null,
      "user_id": null,
      "context": null,
      "exception": null
    },
    {
      "timestamp": "2025-09-01T21:26:13.849570",
      "level": "INFO",
      "message": "线程3日志19",
      "module": "thread_3",
      "function": "",
      "line": 0,
      "thread_id": "19856",
      "task_id": null,
      "user_id": null,
      "context": null,
      "exception": null
    },
    {
      "timestamp": "2025-09-01T21:26:13.849682",
      "level": "INFO",
      "message": "线程0日志17",
      "module": "thread_0",
      "function": "",
      "line": 0,
      "thread_id": "315012",
      "task_id": null,
      "user_id": null,
      "context": null,
      "exception": null
    },
    {
      "timestamp": "2025-09-01T21:26:13.849860",
      "level": "INFO",
      "message": "线程2日志17",
      "module": "thread_2",
      "function": "",
      "line": 0,
      "thread_id": "19368",
      "task_id": null,
      "user_id": null,
      "context": null,
      "exception": null
    },
    {
      "timestamp": "2025-09-01T21:26:13.850058",
      "level": "INFO",
      "message": "线程4日志18",
      "module": "thread_4",
      "function": "",
      "line": 0,
      "thread_id": "283448",
      "task_id": null,
      "user_id": null,
      "context": null,
      "exception": null
    },
    {
      "timestamp": "2025-09-01T21:26:13.850236",
      "level": "INFO",
      "message": "线程0日志18",
      "module": "thread_0",
      "function": "",
      "line": 0,
      "thread_id": "315012",
      "task_id": null,
      "user_id": null,
      "context": null,
      "exception": null
    },
    {
      "timestamp": "2025-09-01T21:26:13.850523",
      "level": "INFO",
      "message": "线程3日志20",
      "module": "thread_3",
      "function": "",
      "line": 0,
      "thread_id": "19856",
      "task_id": null,
      "user_id": null,
      "context": null,
      "exception": null
    },
    {
      "timestamp": "2025-09-01T21:26:13.850654",
      "level": "INFO",
      "message": "线程2日志18",
      "module": "thread_2",
      "function": "",
      "line": 0,
      "thread_id": "19368",
      "task_id": null,
      "user_id": null,
      "context": null,
      "exception": null
    },
    {
      "timestamp": "2025-09-01T21:26:13.850720",
      "level": "INFO",
      "message": "线程1日志20",
      "module": "thread_1",
      "function": "",
      "line": 0,
      "thread_id": "51932",
      "task_id": null,
      "user_id": null,
      "context": null,
      "exception": null
    },
    {
      "timestamp": "2025-09-01T21:26:13.850859",
      "level": "INFO",
      "message": "线程4日志19",
      "module": "thread_4",
      "function": "",
      "line": 0,
      "thread_id": "283448",
      "task_id": null,
      "user_id": null,
      "context": null,
      "exception": null
    },
    {
      "timestamp": "2025-09-01T21:26:13.850998",
      "level": "INFO",
      "message": "线程0日志19",
      "module": "thread_0",
      "function": "",
      "line": 0,
      "thread_id": "315012",
      "task_id": null,
      "user_id": null,
      "context": null,
      "exception": null
    },
    {
      "timestamp": "2025-09-01T21:26:13.851191",
      "level": "INFO",
      "message": "线程1日志21",
      "module": "thread_1",
      "function": "",
      "line": 0,
      "thread_id": "51932",
      "task_id": null,
      "user_id": null,
      "context": null,
      "exception": null
    },
    {
      "timestamp": "2025-09-01T21:26:13.851470",
      "level": "INFO",
      "message": "线程3日志21",
      "module": "thread_3",
      "function": "",
      "line": 0,
      "thread_id": "19856",
      "task_id": null,
      "user_id": null,
      "context": null,
      "exception": null
    },
    {
      "timestamp": "2025-09-01T21:26:13.851549",
      "level": "INFO",
      "message": "线程4日志20",
      "module": "thread_4",
      "function": "",
      "line": 0,
      "thread_id": "283448",
      "task_id": null,
      "user_id": null,
      "context": null,
      "exception": null
    },
    {
      "timestamp": "2025-09-01T21:26:13.851623",
      "level": "INFO",
      "message": "线程2日志19",
      "module": "thread_2",
      "function": "",
      "line": 0,
      "thread_id": "19368",
      "task_id": null,
      "user_id": null,
      "context": null,
      "exception": null
    },
    {
      "timestamp": "2025-09-01T21:26:13.851769",
      "level": "INFO",
      "message": "线程0日志20",
      "module": "thread_0",
      "function": "",
      "line": 0,
      "thread_id": "315012",
      "task_id": null,
      "user_id": null,
      "context": null,
      "exception": null
    },
    {
      "timestamp": "2025-09-01T21:26:13.851919",
      "level": "INFO",
      "message": "线程1日志22",
      "module": "thread_1",
      "function": "",
      "line": 0,
      "thread_id": "51932",
      "task_id": null,
      "user_id": null,
      "context": null,
      "exception": null
    },
    {
      "timestamp": "2025-09-01T21:26:13.852041",
      "level": "INFO",
      "message": "线程2日志20",
      "module": "thread_2",
      "function": "",
      "line": 0,
      "thread_id": "19368",
      "task_id": null,
      "user_id": null,
      "context": null,
      "exception": null
    },
    {
      "timestamp": "2025-09-01T21:26:13.852180",
      "level": "INFO",
      "message": "线程3日志22",
      "module": "thread_3",
      "function": "",
      "line": 0,
      "thread_id": "19856",
      "task_id": null,
      "user_id": null,
      "context": null,
      "exception": null
    },
    {
      "timestamp": "2025-09-01T21:26:13.852324",
      "level": "INFO",
      "message": "线程4日志21",
      "module": "thread_4",
      "function": "",
      "line": 0,
      "thread_id": "283448",
      "task_id": null,
      "user_id": null,
      "context": null,
      "exception": null
    },
    {
      "timestamp": "2025-09-01T21:26:13.852572",
      "level": "INFO",
      "message": "线程2日志21",
      "module": "thread_2",
      "function": "",
      "line": 0,
      "thread_id": "19368",
      "task_id": null,
      "user_id": null,
      "context": null,
      "exception": null
    },
    {
      "timestamp": "2025-09-01T21:26:13.852654",
      "level": "INFO",
      "message": "线程1日志23",
      "module": "thread_1",
      "function": "",
      "line": 0,
      "thread_id": "51932",
      "task_id": null,
      "user_id": null,
      "context": null,
      "exception": null
    },
    {
      "timestamp": "2025-09-01T21:26:13.852885",
      "level": "INFO",
      "message": "线程4日志22",
      "module": "thread_4",
      "function": "",
      "line": 0,
      "thread_id": "283448",
      "task_id": null,
      "user_id": null,
      "context": null,
      "exception": null
    },
    {
      "timestamp": "2025-09-01T21:26:13.853055",
      "level": "INFO",
      "message": "线程0日志21",
      "module": "thread_0",
      "function": "",
      "line": 0,
      "thread_id": "315012",
      "task_id": null,
      "user_id": null,
      "context": null,
      "exception": null
    },
    {
      "timestamp": "2025-09-01T21:26:13.853220",
      "level": "INFO",
      "message": "线程3日志23",
      "module": "thread_3",
      "function": "",
      "line": 0,
      "thread_id": "19856",
      "task_id": null,
      "user_id": null,
      "context": null,
      "exception": null
    },
    {
      "timestamp": "2025-09-01T21:26:13.853414",
      "level": "INFO",
      "message": "线程2日志22",
      "module": "thread_2",
      "function": "",
      "line": 0,
      "thread_id": "19368",
      "task_id": null,
      "user_id": null,
      "context": null,
      "exception": null
    },
    {
      "timestamp": "2025-09-01T21:26:13.853501",
      "level": "INFO",
      "message": "线程1日志24",
      "module": "thread_1",
      "function": "",
      "line": 0,
      "thread_id": "51932",
      "task_id": null,
      "user_id": null,
      "context": null,
      "exception": null
    },
    {
      "timestamp": "2025-09-01T21:26:13.853683",
      "level": "INFO",
      "message": "线程4日志23",
      "module": "thread_4",
      "function": "",
      "line": 0,
      "thread_id": "283448",
      "task_id": null,
      "user_id": null,
      "context": null,
      "exception": null
    },
    {
      "timestamp": "2025-09-01T21:26:13.853880",
      "level": "INFO",
      "message": "线程3日志24",
      "module": "thread_3",
      "function": "",
      "line": 0,
      "thread_id": "19856",
      "task_id": null,
      "user_id": null,
      "context": null,
      "exception": null
    },
    {
      "timestamp": "2025-09-01T21:26:13.853948",
      "level": "INFO",
      "message": "线程2日志23",
      "module": "thread_2",
      "function": "",
      "line": 0,
      "thread_id": "19368",
      "task_id": null,
      "user_id": null,
      "context": null,
      "exception": null
    },
    {
      "timestamp": "2025-09-01T21:26:13.854036",
      "level": "INFO",
      "message": "线程0日志22",
      "module": "thread_0",
      "function": "",
      "line": 0,
      "thread_id": "315012",
      "task_id": null,
      "user_id": null,
      "context": null,
      "exception": null
    },
    {
      "timestamp": "2025-09-01T21:26:13.854170",
      "level": "INFO",
      "message": "线程1日志25",
      "module": "thread_1",
      "function": "",
      "line": 0,
      "thread_id": "51932",
      "task_id": null,
      "user_id": null,
      "context": null,
      "exception": null
    },
    {
      "timestamp": "2025-09-01T21:26:13.854337",
      "level": "INFO",
      "message": "线程4日志24",
      "module": "thread_4",
      "function": "",
      "line": 0,
      "thread_id": "283448",
      "task_id": null,
      "user_id": null,
      "context": null,
      "exception": null
    },
    {
      "timestamp": "2025-09-01T21:26:13.854540",
      "level": "INFO",
      "message": "线程3日志25",
      "module": "thread_3",
      "function": "",
      "line": 0,
      "thread_id": "19856",
      "task_id": null,
      "user_id": null,
      "context": null,
      "exception": null
    },
    {
      "timestamp": "2025-09-01T21:26:13.854623",
      "level": "INFO",
      "message": "线程2日志24",
      "module": "thread_2",
      "function": "",
      "line": 0,
      "thread_id": "19368",
      "task_id": null,
      "user_id": null,
      "context": null,
      "exception": null
    },
    {
      "timestamp": "2025-09-01T21:26:13.854875",
      "level": "INFO",
      "message": "线程1日志26",
      "module": "thread_1",
      "function": "",
      "line": 0,
      "thread_id": "51932",
      "task_id": null,
      "user_id": null,
      "context": null,
      "exception": null
    },
    {
      "timestamp": "2025-09-01T21:26:13.855057",
      "level": "INFO",
      "message": "线程0日志23",
      "module": "thread_0",
      "function": "",
      "line": 0,
      "thread_id": "315012",
      "task_id": null,
      "user_id": null,
      "context": null,
      "exception": null
    },
    {
      "timestamp": "2025-09-01T21:26:13.855173",
      "level": "INFO",
      "message": "线程2日志25",
      "module": "thread_2",
      "function": "",
      "line": 0,
      "thread_id": "19368",
      "task_id": null,
      "user_id": null,
      "context": null,
      "exception": null
    },
    {
      "timestamp": "2025-09-01T21:26:13.855269",
      "level": "INFO",
      "message": "线程4日志25",
      "module": "thread_4",
      "function": "",
      "line": 0,
      "thread_id": "283448",
      "task_id": null,
      "user_id": null,
      "context": null,
      "exception": null
    },
    {
      "timestamp": "2025-09-01T21:26:13.855358",
      "level": "INFO",
      "message": "线程3日志26",
      "module": "thread_3",
      "function": "",
      "line": 0,
      "thread_id": "19856",
      "task_id": null,
      "user_id": null,
      "context": null,
      "exception": null
    },
    {
      "timestamp": "2025-09-01T21:26:13.855479",
      "level": "INFO",
      "message": "线程1日志27",
      "module": "thread_1",
      "function": "",
      "line": 0,
      "thread_id": "51932",
      "task_id": null,
      "user_id": null,
      "context": null,
      "exception": null
    },
    {
      "timestamp": "2025-09-01T21:26:13.855615",
      "level": "INFO",
      "message": "线程0日志24",
      "module": "thread_0",
      "function": "",
      "line": 0,
      "thread_id": "315012",
      "task_id": null,
      "user_id": null,
      "context": null,
      "exception": null
    },
    {
      "timestamp": "2025-09-01T21:26:13.855897",
      "level": "INFO",
      "message": "线程4日志26",
      "module": "thread_4",
      "function": "",
      "line": 0,
      "thread_id": "283448",
      "task_id": null,
      "user_id": null,
      "context": null,
      "exception": null
    },
    {
      "timestamp": "2025-09-01T21:26:13.856278",
      "level": "INFO",
      "message": "线程2日志26",
      "module": "thread_2",
      "function": "",
      "line": 0,
      "thread_id": "19368",
      "task_id": null,
      "user_id": null,
      "context": null,
      "exception": null
    },
    {
      "timestamp": "2025-09-01T21:26:13.856427",
      "level": "INFO",
      "message": "线程1日志28",
      "module": "thread_1",
      "function": "",
      "line": 0,
      "thread_id": "51932",
      "task_id": null,
      "user_id": null,
      "context": null,
      "exception": null
    },
    {
      "timestamp": "2025-09-01T21:26:13.856533",
      "level": "INFO",
      "message": "线程3日志27",
      "module": "thread_3",
      "function": "",
      "line": 0,
      "thread_id": "19856",
      "task_id": null,
      "user_id": null,
      "context": null,
      "exception": null
    },
    {
      "timestamp": "2025-09-01T21:26:13.856622",
      "level": "INFO",
      "message": "线程0日志25",
      "module": "thread_0",
      "function": "",
      "line": 0,
      "thread_id": "315012",
      "task_id": null,
      "user_id": null,
      "context": null,
      "exception": null
    },
    {
      "timestamp": "2025-09-01T21:26:13.856835",
      "level": "INFO",
      "message": "线程4日志27",
      "module": "thread_4",
      "function": "",
      "line": 0,
      "thread_id": "283448",
      "task_id": null,
      "user_id": null,
      "context": null,
      "exception": null
    },
    {
      "timestamp": "2025-09-01T21:26:13.857096",
      "level": "INFO",
      "message": "线程2日志27",
      "module": "thread_2",
      "function": "",
      "line": 0,
      "thread_id": "19368",
      "task_id": null,
      "user_id": null,
      "context": null,
      "exception": null
    },
    {
      "timestamp": "2025-09-01T21:26:13.857273",
      "level": "INFO",
      "message": "线程0日志26",
      "module": "thread_0",
      "function": "",
      "line": 0,
      "thread_id": "315012",
      "task_id": null,
      "user_id": null,
      "context": null,
      "exception": null
    },
    {
      "timestamp": "2025-09-01T21:26:13.857344",
      "level": "INFO",
      "message": "线程1日志29",
      "module": "thread_1",
      "function": "",
      "line": 0,
      "thread_id": "51932",
      "task_id": null,
      "user_id": null,
      "context": null,
      "exception": null
    },
    {
      "timestamp": "2025-09-01T21:26:13.857540",
      "level": "INFO",
      "message": "线程4日志28",
      "module": "thread_4",
      "function": "",
      "line": 0,
      "thread_id": "283448",
      "task_id": null,
      "user_id": null,
      "context": null,
      "exception": null
    },
    {
      "timestamp": "2025-09-01T21:26:13.857782",
      "level": "INFO",
      "message": "线程3日志28",
      "module": "thread_3",
      "function": "",
      "line": 0,
      "thread_id": "19856",
      "task_id": null,
      "user_id": null,
      "context": null,
      "exception": null
    },
    {
      "timestamp": "2025-09-01T21:26:13.858097",
      "level": "INFO",
      "message": "线程2日志28",
      "module": "thread_2",
      "function": "",
      "line": 0,
      "thread_id": "19368",
      "task_id": null,
      "user_id": null,
      "context": null,
      "exception": null
    },
    {
      "timestamp": "2025-09-01T21:26:13.858244",
      "level": "INFO",
      "message": "线程4日志29",
      "module": "thread_4",
      "function": "",
      "line": 0,
      "thread_id": "283448",
      "task_id": null,
      "user_id": null,
      "context": null,
      "exception": null
    },
    {
      "timestamp": "2025-09-01T21:26:13.858323",
      "level": "INFO",
      "message": "线程1日志30",
      "module": "thread_1",
      "function": "",
      "line": 0,
      "thread_id": "51932",
      "task_id": null,
      "user_id": null,
      "context": null,
      "exception": null
    },
    {
      "timestamp": "2025-09-01T21:26:13.858463",
      "level": "INFO",
      "message": "线程0日志27",
      "module": "thread_0",
      "function": "",
      "line": 0,
      "thread_id": "315012",
      "task_id": null,
      "user_id": null,
      "context": null,
      "exception": null
    },
    {
      "timestamp": "2025-09-01T21:26:13.858807",
      "level": "INFO",
      "message": "线程2日志29",
      "module": "thread_2",
      "function": "",
      "line": 0,
      "thread_id": "19368",
      "task_id": null,
      "user_id": null,
      "context": null,
      "exception": null
    },
    {
      "timestamp": "2025-09-01T21:26:13.858914",
      "level": "INFO",
      "message": "线程3日志29",
      "module": "thread_3",
      "function": "",
      "line": 0,
      "thread_id": "19856",
      "task_id": null,
      "user_id": null,
      "context": null,
      "exception": null
    },
    {
      "timestamp": "2025-09-01T21:26:13.859075",
      "level": "INFO",
      "message": "线程4日志30",
      "module": "thread_4",
      "function": "",
      "line": 0,
      "thread_id": "283448",
      "task_id": null,
      "user_id": null,
      "context": null,
      "exception": null
    },
    {
      "timestamp": "2025-09-01T21:26:13.859196",
      "level": "INFO",
      "message": "线程1日志31",
      "module": "thread_1",
      "function": "",
      "line": 0,
      "thread_id": "51932",
      "task_id": null,
      "user_id": null,
      "context": null,
      "exception": null
    },
    {
      "timestamp": "2025-09-01T21:26:13.859275",
      "level": "INFO",
      "message": "线程0日志28",
      "module": "thread_0",
      "function": "",
      "line": 0,
      "thread_id": "315012",
      "task_id": null,
      "user_id": null,
      "context": null,
      "exception": null
    },
    {
      "timestamp": "2025-09-01T21:26:13.859479",
      "level": "INFO",
      "message": "线程3日志30",
      "module": "thread_3",
      "function": "",
      "line": 0,
      "thread_id": "19856",
      "task_id": null,
      "user_id": null,
      "context": null,
      "exception": null
    },
    {
      "timestamp": "2025-09-01T21:26:13.859720",
      "level": "INFO",
      "message": "线程2日志30",
      "module": "thread_2",
      "function": "",
      "line": 0,
      "thread_id": "19368",
      "task_id": null,
      "user_id": null,
      "context": null,
      "exception": null
    },
    {
      "timestamp": "2025-09-01T21:26:13.859854",
      "level": "INFO",
      "message": "线程1日志32",
      "module": "thread_1",
      "function": "",
      "line": 0,
      "thread_id": "51932",
      "task_id": null,
      "user_id": null,
      "context": null,
      "exception": null
    },
    {
      "timestamp": "2025-09-01T21:26:13.859920",
      "level": "INFO",
      "message": "线程4日志31",
      "module": "thread_4",
      "function": "",
      "line": 0,
      "thread_id": "283448",
      "task_id": null,
      "user_id": null,
      "context": null,
      "exception": null
    },
    {
      "timestamp": "2025-09-01T21:26:13.860077",
      "level": "INFO",
      "message": "线程0日志29",
      "module": "thread_0",
      "function": "",
      "line": 0,
      "thread_id": "315012",
      "task_id": null,
      "user_id": null,
      "context": null,
      "exception": null
    },
    {
      "timestamp": "2025-09-01T21:26:13.860187",
      "level": "INFO",
      "message": "线程3日志31",
      "module": "thread_3",
      "function": "",
      "line": 0,
      "thread_id": "19856",
      "task_id": null,
      "user_id": null,
      "context": null,
      "exception": null
    },
    {
      "timestamp": "2025-09-01T21:26:13.860365",
      "level": "INFO",
      "message": "线程1日志33",
      "module": "thread_1",
      "function": "",
      "line": 0,
      "thread_id": "51932",
      "task_id": null,
      "user_id": null,
      "context": null,
      "exception": null
    },
    {
      "timestamp": "2025-09-01T21:26:13.860584",
      "level": "INFO",
      "message": "线程4日志32",
      "module": "thread_4",
      "function": "",
      "line": 0,
      "thread_id": "283448",
      "task_id": null,
      "user_id": null,
      "context": null,
      "exception": null
    },
    {
      "timestamp": "2025-09-01T21:26:13.860776",
      "level": "INFO",
      "message": "线程2日志31",
      "module": "thread_2",
      "function": "",
      "line": 0,
      "thread_id": "19368",
      "task_id": null,
      "user_id": null,
      "context": null,
      "exception": null
    },
    {
      "timestamp": "2025-09-01T21:26:13.860845",
      "level": "INFO",
      "message": "线程3日志32",
      "module": "thread_3",
      "function": "",
      "line": 0,
      "thread_id": "19856",
      "task_id": null,
      "user_id": null,
      "context": null,
      "exception": null
    },
    {
      "timestamp": "2025-09-01T21:26:13.860921",
      "level": "INFO",
      "message": "线程0日志30",
      "module": "thread_0",
      "function": "",
      "line": 0,
      "thread_id": "315012",
      "task_id": null,
      "user_id": null,
      "context": null,
      "exception": null
    },
    {
      "timestamp": "2025-09-01T21:26:13.861163",
      "level": "INFO",
      "message": "线程1日志34",
      "module": "thread_1",
      "function": "",
      "line": 0,
      "thread_id": "51932",
      "task_id": null,
      "user_id": null,
      "context": null,
      "exception": null
    },
    {
      "timestamp": "2025-09-01T21:26:13.861252",
      "level": "INFO",
      "message": "线程4日志33",
      "module": "thread_4",
      "function": "",
      "line": 0,
      "thread_id": "283448",
      "task_id": null,
      "user_id": null,
      "context": null,
      "exception": null
    },
    {
      "timestamp": "2025-09-01T21:26:13.861372",
      "level": "INFO",
      "message": "线程2日志32",
      "module": "thread_2",
      "function": "",
      "line": 0,
      "thread_id": "19368",
      "task_id": null,
      "user_id": null,
      "context": null,
      "exception": null
    },
    {
      "timestamp": "2025-09-01T21:26:13.861479",
      "level": "INFO",
      "message": "线程3日志33",
      "module": "thread_3",
      "function": "",
      "line": 0,
      "thread_id": "19856",
      "task_id": null,
      "user_id": null,
      "context": null,
      "exception": null
    },
    {
      "timestamp": "2025-09-01T21:26:13.861618",
      "level": "INFO",
      "message": "线程0日志31",
      "module": "thread_0",
      "function": "",
      "line": 0,
      "thread_id": "315012",
      "task_id": null,
      "user_id": null,
      "context": null,
      "exception": null
    },
    {
      "timestamp": "2025-09-01T21:26:13.861835",
      "level": "INFO",
      "message": "线程1日志35",
      "module": "thread_1",
      "function": "",
      "line": 0,
      "thread_id": "51932",
      "task_id": null,
      "user_id": null,
      "context": null,
      "exception": null
    },
    {
      "timestamp": "2025-09-01T21:26:13.862002",
      "level": "INFO",
      "message": "线程4日志34",
      "module": "thread_4",
      "function": "",
      "line": 0,
      "thread_id": "283448",
      "task_id": null,
      "user_id": null,
      "context": null,
      "exception": null
    },
    {
      "timestamp": "2025-09-01T21:26:13.862069",
      "level": "INFO",
      "message": "线程0日志32",
      "module": "thread_0",
      "function": "",
      "line": 0,
      "thread_id": "315012",
      "task_id": null,
      "user_id": null,
      "context": null,
      "exception": null
    },
    {
      "timestamp": "2025-09-01T21:26:13.862175",
      "level": "INFO",
      "message": "线程3日志34",
      "module": "thread_3",
      "function": "",
      "line": 0,
      "thread_id": "19856",
      "task_id": null,
      "user_id": null,
      "context": null,
      "exception": null
    },
    {
      "timestamp": "2025-09-01T21:26:13.862307",
      "level": "INFO",
      "message": "线程2日志33",
      "module": "thread_2",
      "function": "",
      "line": 0,
      "thread_id": "19368",
      "task_id": null,
      "user_id": null,
      "context": null,
      "exception": null
    },
    {
      "timestamp": "2025-09-01T21:26:13.862586",
      "level": "INFO",
      "message": "线程1日志36",
      "module": "thread_1",
      "function": "",
      "line": 0,
      "thread_id": "51932",
      "task_id": null,
      "user_id": null,
      "context": null,
      "exception": null
    },
    {
      "timestamp": "2025-09-01T21:26:13.862667",
      "level": "INFO",
      "message": "线程4日志35",
      "module": "thread_4",
      "function": "",
      "line": 0,
      "thread_id": "283448",
      "task_id": null,
      "user_id": null,
      "context": null,
      "exception": null
    },
    {
      "timestamp": "2025-09-01T21:26:13.862776",
      "level": "INFO",
      "message": "线程0日志33",
      "module": "thread_0",
      "function": "",
      "line": 0,
      "thread_id": "315012",
      "task_id": null,
      "user_id": null,
      "context": null,
      "exception": null
    },
    {
      "timestamp": "2025-09-01T21:26:13.862888",
      "level": "INFO",
      "message": "线程2日志34",
      "module": "thread_2",
      "function": "",
      "line": 0,
      "thread_id": "19368",
      "task_id": null,
      "user_id": null,
      "context": null,
      "exception": null
    },
    {
      "timestamp": "2025-09-01T21:26:13.863011",
      "level": "INFO",
      "message": "线程3日志35",
      "module": "thread_3",
      "function": "",
      "line": 0,
      "thread_id": "19856",
      "task_id": null,
      "user_id": null,
      "context": null,
      "exception": null
    },
    {
      "timestamp": "2025-09-01T21:26:13.863219",
      "level": "INFO",
      "message": "线程1日志37",
      "module": "thread_1",
      "function": "",
      "line": 0,
      "thread_id": "51932",
      "task_id": null,
      "user_id": null,
      "context": null,
      "exception": null
    },
    {
      "timestamp": "2025-09-01T21:26:13.863410",
      "level": "INFO",
      "message": "线程4日志36",
      "module": "thread_4",
      "function": "",
      "line": 0,
      "thread_id": "283448",
      "task_id": null,
      "user_id": null,
      "context": null,
      "exception": null
    },
    {
      "timestamp": "2025-09-01T21:26:13.863535",
      "level": "INFO",
      "message": "线程3日志36",
      "module": "thread_3",
      "function": "",
      "line": 0,
      "thread_id": "19856",
      "task_id": null,
      "user_id": null,
      "context": null,
      "exception": null
    },
    {
      "timestamp": "2025-09-01T21:26:13.863609",
      "level": "INFO",
      "message": "线程0日志34",
      "module": "thread_0",
      "function": "",
      "line": 0,
      "thread_id": "315012",
      "task_id": null,
      "user_id": null,
      "context": null,
      "exception": null
    },
    {
      "timestamp": "2025-09-01T21:26:13.863725",
      "level": "INFO",
      "message": "线程2日志35",
      "module": "thread_2",
      "function": "",
      "line": 0,
      "thread_id": "19368",
      "task_id": null,
      "user_id": null,
      "context": null,
      "exception": null
    },
    {
      "timestamp": "2025-09-01T21:26:13.863936",
      "level": "INFO",
      "message": "线程1日志38",
      "module": "thread_1",
      "function": "",
      "line": 0,
      "thread_id": "51932",
      "task_id": null,
      "user_id": null,
      "context": null,
      "exception": null
    },
    {
      "timestamp": "2025-09-01T21:26:13.864061",
      "level": "INFO",
      "message": "线程3日志37",
      "module": "thread_3",
      "function": "",
      "line": 0,
      "thread_id": "19856",
      "task_id": null,
      "user_id": null,
      "context": null,
      "exception": null
    },
    {
      "timestamp": "2025-09-01T21:26:13.864192",
      "level": "INFO",
      "message": "线程0日志35",
      "module": "thread_0",
      "function": "",
      "line": 0,
      "thread_id": "315012",
      "task_id": null,
      "user_id": null,
      "context": null,
      "exception": null
    },
    {
      "timestamp": "2025-09-01T21:26:13.864370",
      "level": "INFO",
      "message": "线程4日志37",
      "module": "thread_4",
      "function": "",
      "line": 0,
      "thread_id": "283448",
      "task_id": null,
      "user_id": null,
      "context": null,
      "exception": null
    },
    {
      "timestamp": "2025-09-01T21:26:13.864504",
      "level": "INFO",
      "message": "线程2日志36",
      "module": "thread_2",
      "function": "",
      "line": 0,
      "thread_id": "19368",
      "task_id": null,
      "user_id": null,
      "context": null,
      "exception": null
    },
    {
      "timestamp": "2025-09-01T21:26:13.864648",
      "level": "INFO",
      "message": "线程3日志38",
      "module": "thread_3",
      "function": "",
      "line": 0,
      "thread_id": "19856",
      "task_id": null,
      "user_id": null,
      "context": null,
      "exception": null
    },
    {
      "timestamp": "2025-09-01T21:26:13.864764",
      "level": "INFO",
      "message": "线程1日志39",
      "module": "thread_1",
      "function": "",
      "line": 0,
      "thread_id": "51932",
      "task_id": null,
      "user_id": null,
      "context": null,
      "exception": null
    },
    {
      "timestamp": "2025-09-01T21:26:13.864900",
      "level": "INFO",
      "message": "线程0日志36",
      "module": "thread_0",
      "function": "",
      "line": 0,
      "thread_id": "315012",
      "task_id": null,
      "user_id": null,
      "context": null,
      "exception": null
    },
    {
      "timestamp": "2025-09-01T21:26:13.865030",
      "level": "INFO",
      "message": "线程2日志37",
      "module": "thread_2",
      "function": "",
      "line": 0,
      "thread_id": "19368",
      "task_id": null,
      "user_id": null,
      "context": null,
      "exception": null
    },
    {
      "timestamp": "2025-09-01T21:26:13.865307",
      "level": "INFO",
      "message": "线程4日志38",
      "module": "thread_4",
      "function": "",
      "line": 0,
      "thread_id": "283448",
      "task_id": null,
      "user_id": null,
      "context": null,
      "exception": null
    },
    {
      "timestamp": "2025-09-01T21:26:13.865481",
      "level": "INFO",
      "message": "线程3日志39",
      "module": "thread_3",
      "function": "",
      "line": 0,
      "thread_id": "19856",
      "task_id": null,
      "user_id": null,
      "context": null,
      "exception": null
    },
    {
      "timestamp": "2025-09-01T21:26:13.865681",
      "level": "INFO",
      "message": "线程2日志38",
      "module": "thread_2",
      "function": "",
      "line": 0,
      "thread_id": "19368",
      "task_id": null,
      "user_id": null,
      "context": null,
      "exception": null
    },
    {
      "timestamp": "2025-09-01T21:26:13.865739",
      "level": "INFO",
      "message": "线程0日志37",
      "module": "thread_0",
      "function": "",
      "line": 0,
      "thread_id": "315012",
      "task_id": null,
      "user_id": null,
      "context": null,
      "exception": null
    },
    {
      "timestamp": "2025-09-01T21:26:13.865801",
      "level": "INFO",
      "message": "线程1日志40",
      "module": "thread_1",
      "function": "",
      "line": 0,
      "thread_id": "51932",
      "task_id": null,
      "user_id": null,
      "context": null,
      "exception": null
    },
    {
      "timestamp": "2025-09-01T21:26:13.865940",
      "level": "INFO",
      "message": "线程4日志39",
      "module": "thread_4",
      "function": "",
      "line": 0,
      "thread_id": "283448",
      "task_id": null,
      "user_id": null,
      "context": null,
      "exception": null
    },
    {
      "timestamp": "2025-09-01T21:26:13.866126",
      "level": "INFO",
      "message": "线程3日志40",
      "module": "thread_3",
      "function": "",
      "line": 0,
      "thread_id": "19856",
      "task_id": null,
      "user_id": null,
      "context": null,
      "exception": null
    },
    {
      "timestamp": "2025-09-01T21:26:13.866328",
      "level": "INFO",
      "message": "线程1日志41",
      "module": "thread_1",
      "function": "",
      "line": 0,
      "thread_id": "51932",
      "task_id": null,
      "user_id": null,
      "context": null,
      "exception": null
    },
    {
      "timestamp": "2025-09-01T21:26:13.866450",
      "level": "INFO",
      "message": "线程2日志39",
      "module": "thread_2",
      "function": "",
      "line": 0,
      "thread_id": "19368",
      "task_id": null,
      "user_id": null,
      "context": null,
      "exception": null
    },
    {
      "timestamp": "2025-09-01T21:26:13.866517",
      "level": "INFO",
      "message": "线程0日志38",
      "module": "thread_0",
      "function": "",
      "line": 0,
      "thread_id": "315012",
      "task_id": null,
      "user_id": null,
      "context": null,
      "exception": null
    },
    {
      "timestamp": "2025-09-01T21:26:13.866699",
      "level": "INFO",
      "message": "线程3日志41",
      "module": "thread_3",
      "function": "",
      "line": 0,
      "thread_id": "19856",
      "task_id": null,
      "user_id": null,
      "context": null,
      "exception": null
    },
    {
      "timestamp": "2025-09-01T21:26:13.866961",
      "level": "INFO",
      "message": "线程1日志42",
      "module": "thread_1",
      "function": "",
      "line": 0,
      "thread_id": "51932",
      "task_id": null,
      "user_id": null,
      "context": null,
      "exception": null
    },
    {
      "timestamp": "2025-09-01T21:26:13.867024",
      "level": "INFO",
      "message": "线程4日志40",
      "module": "thread_4",
      "function": "",
      "line": 0,
      "thread_id": "283448",
      "task_id": null,
      "user_id": null,
      "context": null,
      "exception": null
    },
    {
      "timestamp": "2025-09-01T21:26:13.867152",
      "level": "INFO",
      "message": "线程0日志39",
      "module": "thread_0",
      "function": "",
      "line": 0,
      "thread_id": "315012",
      "task_id": null,
      "user_id": null,
      "context": null,
      "exception": null
    },
    {
      "timestamp": "2025-09-01T21:26:13.867245",
      "level": "INFO",
      "message": "线程2日志40",
      "module": "thread_2",
      "function": "",
      "line": 0,
      "thread_id": "19368",
      "task_id": null,
      "user_id": null,
      "context": null,
      "exception": null
    },
    {
      "timestamp": "2025-09-01T21:26:13.867428",
      "level": "INFO",
      "message": "线程3日志42",
      "module": "thread_3",
      "function": "",
      "line": 0,
      "thread_id": "19856",
      "task_id": null,
      "user_id": null,
      "context": null,
      "exception": null
    },
    {
      "timestamp": "2025-09-01T21:26:13.867660",
      "level": "INFO",
      "message": "线程4日志41",
      "module": "thread_4",
      "function": "",
      "line": 0,
      "thread_id": "283448",
      "task_id": null,
      "user_id": null,
      "context": null,
      "exception": null
    },
    {
      "timestamp": "2025-09-01T21:26:13.867737",
      "level": "INFO",
      "message": "线程0日志40",
      "module": "thread_0",
      "function": "",
      "line": 0,
      "thread_id": "315012",
      "task_id": null,
      "user_id": null,
      "context": null,
      "exception": null
    },
    {
      "timestamp": "2025-09-01T21:26:13.867803",
      "level": "INFO",
      "message": "线程1日志43",
      "module": "thread_1",
      "function": "",
      "line": 0,
      "thread_id": "51932",
      "task_id": null,
      "user_id": null,
      "context": null,
      "exception": null
    },
    {
      "timestamp": "2025-09-01T21:26:13.867981",
      "level": "INFO",
      "message": "线程2日志41",
      "module": "thread_2",
      "function": "",
      "line": 0,
      "thread_id": "19368",
      "task_id": null,
      "user_id": null,
      "context": null,
      "exception": null
    },
    {
      "timestamp": "2025-09-01T21:26:13.868119",
      "level": "INFO",
      "message": "线程4日志42",
      "module": "thread_4",
      "function": "",
      "line": 0,
      "thread_id": "283448",
      "task_id": null,
      "user_id": null,
      "context": null,
      "exception": null
    },
    {
      "timestamp": "2025-09-01T21:26:13.868356",
      "level": "INFO",
      "message": "线程0日志41",
      "module": "thread_0",
      "function": "",
      "line": 0,
      "thread_id": "315012",
      "task_id": null,
      "user_id": null,
      "context": null,
      "exception": null
    },
    {
      "timestamp": "2025-09-01T21:26:13.868421",
      "level": "INFO",
      "message": "线程3日志43",
      "module": "thread_3",
      "function": "",
      "line": 0,
      "thread_id": "19856",
      "task_id": null,
      "user_id": null,
      "context": null,
      "exception": null
    },
    {
      "timestamp": "2025-09-01T21:26:13.868542",
      "level": "INFO",
      "message": "线程1日志44",
      "module": "thread_1",
      "function": "",
      "line": 0,
      "thread_id": "51932",
      "task_id": null,
      "user_id": null,
      "context": null,
      "exception": null
    },
    {
      "timestamp": "2025-09-01T21:26:13.868597",
      "level": "INFO",
      "message": "线程2日志42",
      "module": "thread_2",
      "function": "",
      "line": 0,
      "thread_id": "19368",
      "task_id": null,
      "user_id": null,
      "context": null,
      "exception": null
    },
    {
      "timestamp": "2025-09-01T21:26:13.868879",
      "level": "INFO",
      "message": "线程0日志42",
      "module": "thread_0",
      "function": "",
      "line": 0,
      "thread_id": "315012",
      "task_id": null,
      "user_id": null,
      "context": null,
      "exception": null
    },
    {
      "timestamp": "2025-09-01T21:26:13.869015",
      "level": "INFO",
      "message": "线程3日志44",
      "module": "thread_3",
      "function": "",
      "line": 0,
      "thread_id": "19856",
      "task_id": null,
      "user_id": null,
      "context": null,
      "exception": null
    },
    {
      "timestamp": "2025-09-01T21:26:13.869152",
      "level": "INFO",
      "message": "线程2日志43",
      "module": "thread_2",
      "function": "",
      "line": 0,
      "thread_id": "19368",
      "task_id": null,
      "user_id": null,
      "context": null,
      "exception": null
    },
    {
      "timestamp": "2025-09-01T21:26:13.869278",
      "level": "INFO",
      "message": "线程1日志45",
      "module": "thread_1",
      "function": "",
      "line": 0,
      "thread_id": "51932",
      "task_id": null,
      "user_id": null,
      "context": null,
      "exception": null
    },
    {
      "timestamp": "2025-09-01T21:26:13.869332",
      "level": "INFO",
      "message": "线程4日志43",
      "module": "thread_4",
      "function": "",
      "line": 0,
      "thread_id": "283448",
      "task_id": null,
      "user_id": null,
      "context": null,
      "exception": null
    },
    {
      "timestamp": "2025-09-01T21:26:13.869575",
      "level": "INFO",
      "message": "线程3日志45",
      "module": "thread_3",
      "function": "",
      "line": 0,
      "thread_id": "19856",
      "task_id": null,
      "user_id": null,
      "context": null,
      "exception": null
    },
    {
      "timestamp": "2025-09-01T21:26:13.869797",
      "level": "INFO",
      "message": "线程0日志43",
      "module": "thread_0",
      "function": "",
      "line": 0,
      "thread_id": "315012",
      "task_id": null,
      "user_id": null,
      "context": null,
      "exception": null
    },
    {
      "timestamp": "2025-09-01T21:26:13.869908",
      "level": "INFO",
      "message": "线程2日志44",
      "module": "thread_2",
      "function": "",
      "line": 0,
      "thread_id": "19368",
      "task_id": null,
      "user_id": null,
      "context": null,
      "exception": null
    },
    {
      "timestamp": "2025-09-01T21:26:13.869974",
      "level": "INFO",
      "message": "线程1日志46",
      "module": "thread_1",
      "function": "",
      "line": 0,
      "thread_id": "51932",
      "task_id": null,
      "user_id": null,
      "context": null,
      "exception": null
    },
    {
      "timestamp": "2025-09-01T21:26:13.870100",
      "level": "INFO",
      "message": "线程3日志46",
      "module": "thread_3",
      "function": "",
      "line": 0,
      "thread_id": "19856",
      "task_id": null,
      "user_id": null,
      "context": null,
      "exception": null
    },
    {
      "timestamp": "2025-09-01T21:26:13.870280",
      "level": "INFO",
      "message": "线程4日志44",
      "module": "thread_4",
      "function": "",
      "line": 0,
      "thread_id": "283448",
      "task_id": null,
      "user_id": null,
      "context": null,
      "exception": null
    },
    {
      "timestamp": "2025-09-01T21:26:13.870529",
      "level": "INFO",
      "message": "线程0日志44",
      "module": "thread_0",
      "function": "",
      "line": 0,
      "thread_id": "315012",
      "task_id": null,
      "user_id": null,
      "context": null,
      "exception": null
    },
    {
      "timestamp": "2025-09-01T21:26:13.870599",
      "level": "INFO",
      "message": "线程2日志45",
      "module": "thread_2",
      "function": "",
      "line": 0,
      "thread_id": "19368",
      "task_id": null,
      "user_id": null,
      "context": null,
      "exception": null
    },
    {
      "timestamp": "2025-09-01T21:26:13.870728",
      "level": "INFO",
      "message": "线程1日志47",
      "module": "thread_1",
      "function": "",
      "line": 0,
      "thread_id": "51932",
      "task_id": null,
      "user_id": null,
      "context": null,
      "exception": null
    },
    {
      "timestamp": "2025-09-01T21:26:13.870891",
      "level": "INFO",
      "message": "线程3日志47",
      "module": "thread_3",
      "function": "",
      "line": 0,
      "thread_id": "19856",
      "task_id": null,
      "user_id": null,
      "context": null,
      "exception": null
    },
    {
      "timestamp": "2025-09-01T21:26:13.871098",
      "level": "INFO",
      "message": "线程0日志45",
      "module": "thread_0",
      "function": "",
      "line": 0,
      "thread_id": "315012",
      "task_id": null,
      "user_id": null,
      "context": null,
      "exception": null
    },
    {
      "timestamp": "2025-09-01T21:26:13.871281",
      "level": "INFO",
      "message": "线程2日志46",
      "module": "thread_2",
      "function": "",
      "line": 0,
      "thread_id": "19368",
      "task_id": null,
      "user_id": null,
      "context": null,
      "exception": null
    },
    {
      "timestamp": "2025-09-01T21:26:13.871469",
      "level": "INFO",
      "message": "线程1日志48",
      "module": "thread_1",
      "function": "",
      "line": 0,
      "thread_id": "51932",
      "task_id": null,
      "user_id": null,
      "context": null,
      "exception": null
    },
    {
      "timestamp": "2025-09-01T21:26:13.871577",
      "level": "INFO",
      "message": "线程3日志48",
      "module": "thread_3",
      "function": "",
      "line": 0,
      "thread_id": "19856",
      "task_id": null,
      "user_id": null,
      "context": null,
      "exception": null
    },
    {
      "timestamp": "2025-09-01T21:26:13.871745",
      "level": "INFO",
      "message": "线程4日志45",
      "module": "thread_4",
      "function": "",
      "line": 0,
      "thread_id": "283448",
      "task_id": null,
      "user_id": null,
      "context": null,
      "exception": null
    },
    {
      "timestamp": "2025-09-01T21:26:13.871840",
      "level": "INFO",
      "message": "线程2日志47",
      "module": "thread_2",
      "function": "",
      "line": 0,
      "thread_id": "19368",
      "task_id": null,
      "user_id": null,
      "context": null,
      "exception": null
    },
    {
      "timestamp": "2025-09-01T21:26:13.872028",
      "level": "INFO",
      "message": "线程0日志46",
      "module": "thread_0",
      "function": "",
      "line": 0,
      "thread_id": "315012",
      "task_id": null,
      "user_id": null,
      "context": null,
      "exception": null
    },
    {
      "timestamp": "2025-09-01T21:26:13.872128",
      "level": "INFO",
      "message": "线程3日志49",
      "module": "thread_3",
      "function": "",
      "line": 0,
      "thread_id": "19856",
      "task_id": null,
      "user_id": null,
      "context": null,
      "exception": null
    },
    {
      "timestamp": "2025-09-01T21:26:13.872261",
      "level": "INFO",
      "message": "线程4日志46",
      "module": "thread_4",
      "function": "",
      "line": 0,
      "thread_id": "283448",
      "task_id": null,
      "user_id": null,
      "context": null,
      "exception": null
    },
    {
      "timestamp": "2025-09-01T21:26:13.872402",
      "level": "INFO",
      "message": "线程2日志48",
      "module": "thread_2",
      "function": "",
      "line": 0,
      "thread_id": "19368",
      "task_id": null,
      "user_id": null,
      "context": null,
      "exception": null
    },
    {
      "timestamp": "2025-09-01T21:26:13.872552",
      "level": "INFO",
      "message": "线程1日志49",
      "module": "thread_1",
      "function": "",
      "line": 0,
      "thread_id": "51932",
      "task_id": null,
      "user_id": null,
      "context": null,
      "exception": null
    },
    {
      "timestamp": "2025-09-01T21:26:13.872754",
      "level": "INFO",
      "message": "线程4日志47",
      "module": "thread_4",
      "function": "",
      "line": 0,
      "thread_id": "283448",
      "task_id": null,
      "user_id": null,
      "context": null,
      "exception": null
    },
    {
      "timestamp": "2025-09-01T21:26:13.873077",
      "level": "INFO",
      "message": "线程2日志49",
      "module": "thread_2",
      "function": "",
      "line": 0,
      "thread_id": "19368",
      "task_id": null,
      "user_id": null,
      "context": null,
      "exception": null
    },
    {
      "timestamp": "2025-09-01T21:26:13.873355",
      "level": "INFO",
      "message": "线程4日志48",
      "module": "thread_4",
      "function": "",
      "line": 0,
      "thread_id": "283448",
      "task_id": null,
      "user_id": null,
      "context": null,
      "exception": null
    },
    {
      "timestamp": "2025-09-01T21:26:13.873460",
      "level": "INFO",
      "message": "线程0日志47",
      "module": "thread_0",
      "function": "",
      "line": 0,
      "thread_id": "315012",
      "task_id": null,
      "user_id": null,
      "context": null,
      "exception": null
    },
    {
      "timestamp": "2025-09-01T21:26:13.873807",
      "level": "INFO",
      "message": "线程4日志49",
      "module": "thread_4",
      "function": "",
      "line": 0,
      "thread_id": "283448",
      "task_id": null,
      "user_id": null,
      "context": null,
      "exception": null
    },
    {
      "timestamp": "2025-09-01T21:26:13.874000",
      "level": "INFO",
      "message": "线程0日志48",
      "module": "thread_0",
      "function": "",
      "line": 0,
      "thread_id": "315012",
      "task_id": null,
      "user_id": null,
      "context": null,
      "exception": null
    },
    {
      "timestamp": "2025-09-01T21:26:13.874384",
      "level": "INFO",
      "message": "线程0日志49",
      "module": "thread_0",
      "function": "",
      "line": 0,
      "thread_id": "315012",
      "task_id": null,
      "user_id": null,
      "context": null,
      "exception": null
    }
  ]
}