{
  "export_time": "2025-09-02T02:10:50.140012",
  "log_count": 250,
  "logs": [
    {
      "timestamp": "2025-09-02T02:10:42.136695",
      "level": "INFO",
      "message": "线程0日志0",
      "module": "thread_0",
      "function": "",
      "line": 0,
      "thread_id": "94620",
      "task_id": null,
      "user_id": null,
      "context": null,
      "exception": null
    },
    {
      "timestamp": "2025-09-02T02:10:42.136938",
      "level": "INFO",
      "message": "线程1日志0",
      "module": "thread_1",
      "function": "",
      "line": 0,
      "thread_id": "122196",
      "task_id": null,
      "user_id": null,
      "context": null,
      "exception": null
    },
    {
      "timestamp": "2025-09-02T02:10:42.137172",
      "level": "INFO",
      "message": "线程2日志0",
      "module": "thread_2",
      "function": "",
      "line": 0,
      "thread_id": "141444",
      "task_id": null,
      "user_id": null,
      "context": null,
      "exception": null
    },
    {
      "timestamp": "2025-09-02T02:10:42.137439",
      "level": "INFO",
      "message": "线程0日志1",
      "module": "thread_0",
      "function": "",
      "line": 0,
      "thread_id": "94620",
      "task_id": null,
      "user_id": null,
      "context": null,
      "exception": null
    },
    {
      "timestamp": "2025-09-02T02:10:42.137673",
      "level": "INFO",
      "message": "线程1日志1",
      "module": "thread_1",
      "function": "",
      "line": 0,
      "thread_id": "122196",
      "task_id": null,
      "user_id": null,
      "context": null,
      "exception": null
    },
    {
      "timestamp": "2025-09-02T02:10:42.137768",
      "level": "INFO",
      "message": "线程3日志0",
      "module": "thread_3",
      "function": "",
      "line": 0,
      "thread_id": "128036",
      "task_id": null,
      "user_id": null,
      "context": null,
      "exception": null
    },
    {
      "timestamp": "2025-09-02T02:10:42.138206",
      "level": "INFO",
      "message": "线程2日志1",
      "module": "thread_2",
      "function": "",
      "line": 0,
      "thread_id": "141444",
      "task_id": null,
      "user_id": null,
      "context": null,
      "exception": null
    },
    {
      "timestamp": "2025-09-02T02:10:42.138317",
      "level": "INFO",
      "message": "线程4日志0",
      "module": "thread_4",
      "function": "",
      "line": 0,
      "thread_id": "34996",
      "task_id": null,
      "user_id": null,
      "context": null,
      "exception": null
    },
    {
      "timestamp": "2025-09-02T02:10:42.138537",
      "level": "INFO",
      "message": "线程1日志2",
      "module": "thread_1",
      "function": "",
      "line": 0,
      "thread_id": "122196",
      "task_id": null,
      "user_id": null,
      "context": null,
      "exception": null
    },
    {
      "timestamp": "2025-09-02T02:10:42.138777",
      "level": "INFO",
      "message": "线程3日志1",
      "module": "thread_3",
      "function": "",
      "line": 0,
      "thread_id": "128036",
      "task_id": null,
      "user_id": null,
      "context": null,
      "exception": null
    },
    {
      "timestamp": "2025-09-02T02:10:42.138863",
      "level": "INFO",
      "message": "线程0日志2",
      "module": "thread_0",
      "function": "",
      "line": 0,
      "thread_id": "94620",
      "task_id": null,
      "user_id": null,
      "context": null,
      "exception": null
    },
    {
      "timestamp": "2025-09-02T02:10:42.139183",
      "level": "INFO",
      "message": "线程4日志1",
      "module": "thread_4",
      "function": "",
      "line": 0,
      "thread_id": "34996",
      "task_id": null,
      "user_id": null,
      "context": null,
      "exception": null
    },
    {
      "timestamp": "2025-09-02T02:10:42.139394",
      "level": "INFO",
      "message": "线程0日志3",
      "module": "thread_0",
      "function": "",
      "line": 0,
      "thread_id": "94620",
      "task_id": null,
      "user_id": null,
      "context": null,
      "exception": null
    },
    {
      "timestamp": "2025-09-02T02:10:42.139540",
      "level": "INFO",
      "message": "线程1日志3",
      "module": "thread_1",
      "function": "",
      "line": 0,
      "thread_id": "122196",
      "task_id": null,
      "user_id": null,
      "context": null,
      "exception": null
    },
    {
      "timestamp": "2025-09-02T02:10:42.139670",
      "level": "INFO",
      "message": "线程3日志2",
      "module": "thread_3",
      "function": "",
      "line": 0,
      "thread_id": "128036",
      "task_id": null,
      "user_id": null,
      "context": null,
      "exception": null
    },
    {
      "timestamp": "2025-09-02T02:10:42.139771",
      "level": "INFO",
      "message": "线程2日志2",
      "module": "thread_2",
      "function": "",
      "line": 0,
      "thread_id": "141444",
      "task_id": null,
      "user_id": null,
      "context": null,
      "exception": null
    },
    {
      "timestamp": "2025-09-02T02:10:42.139993",
      "level": "INFO",
      "message": "线程4日志2",
      "module": "thread_4",
      "function": "",
      "line": 0,
      "thread_id": "34996",
      "task_id": null,
      "user_id": null,
      "context": null,
      "exception": null
    },
    {
      "timestamp": "2025-09-02T02:10:42.140204",
      "level": "INFO",
      "message": "线程2日志3",
      "module": "thread_2",
      "function": "",
      "line": 0,
      "thread_id": "141444",
      "task_id": null,
      "user_id": null,
      "context": null,
      "exception": null
    },
    {
      "timestamp": "2025-09-02T02:10:42.140410",
      "level": "INFO",
      "message": "线程1日志4",
      "module": "thread_1",
      "function": "",
      "line": 0,
      "thread_id": "122196",
      "task_id": null,
      "user_id": null,
      "context": null,
      "exception": null
    },
    {
      "timestamp": "2025-09-02T02:10:42.140506",
      "level": "INFO",
      "message": "线程0日志4",
      "module": "thread_0",
      "function": "",
      "line": 0,
      "thread_id": "94620",
      "task_id": null,
      "user_id": null,
      "context": null,
      "exception": null
    },
    {
      "timestamp": "2025-09-02T02:10:42.140638",
      "level": "INFO",
      "message": "线程4日志3",
      "module": "thread_4",
      "function": "",
      "line": 0,
      "thread_id": "34996",
      "task_id": null,
      "user_id": null,
      "context": null,
      "exception": null
    },
    {
      "timestamp": "2025-09-02T02:10:42.140966",
      "level": "INFO",
      "message": "线程3日志3",
      "module": "thread_3",
      "function": "",
      "line": 0,
      "thread_id": "128036",
      "task_id": null,
      "user_id": null,
      "context": null,
      "exception": null
    },
    {
      "timestamp": "2025-09-02T02:10:42.141257",
      "level": "INFO",
      "message": "线程2日志4",
      "module": "thread_2",
      "function": "",
      "line": 0,
      "thread_id": "141444",
      "task_id": null,
      "user_id": null,
      "context": null,
      "exception": null
    },
    {
      "timestamp": "2025-09-02T02:10:42.141467",
      "level": "INFO",
      "message": "线程1日志5",
      "module": "thread_1",
      "function": "",
      "line": 0,
      "thread_id": "122196",
      "task_id": null,
      "user_id": null,
      "context": null,
      "exception": null
    },
    {
      "timestamp": "2025-09-02T02:10:42.141705",
      "level": "INFO",
      "message": "线程4日志4",
      "module": "thread_4",
      "function": "",
      "line": 0,
      "thread_id": "34996",
      "task_id": null,
      "user_id": null,
      "context": null,
      "exception": null
    },
    {
      "timestamp": "2025-09-02T02:10:42.141952",
      "level": "INFO",
      "message": "线程0日志5",
      "module": "thread_0",
      "function": "",
      "line": 0,
      "thread_id": "94620",
      "task_id": null,
      "user_id": null,
      "context": null,
      "exception": null
    },
    {
      "timestamp": "2025-09-02T02:10:42.142311",
      "level": "INFO",
      "message": "线程3日志4",
      "module": "thread_3",
      "function": "",
      "line": 0,
      "thread_id": "128036",
      "task_id": null,
      "user_id": null,
      "context": null,
      "exception": null
    },
    {
      "timestamp": "2025-09-02T02:10:42.142619",
      "level": "INFO",
      "message": "线程1日志6",
      "module": "thread_1",
      "function": "",
      "line": 0,
      "thread_id": "122196",
      "task_id": null,
      "user_id": null,
      "context": null,
      "exception": null
    },
    {
      "timestamp": "2025-09-02T02:10:42.142779",
      "level": "INFO",
      "message": "线程2日志5",
      "module": "thread_2",
      "function": "",
      "line": 0,
      "thread_id": "141444",
      "task_id": null,
      "user_id": null,
      "context": null,
      "exception": null
    },
    {
      "timestamp": "2025-09-02T02:10:42.142950",
      "level": "INFO",
      "message": "线程0日志6",
      "module": "thread_0",
      "function": "",
      "line": 0,
      "thread_id": "94620",
      "task_id": null,
      "user_id": null,
      "context": null,
      "exception": null
    },
    {
      "timestamp": "2025-09-02T02:10:42.143110",
      "level": "INFO",
      "message": "线程4日志5",
      "module": "thread_4",
      "function": "",
      "line": 0,
      "thread_id": "34996",
      "task_id": null,
      "user_id": null,
      "context": null,
      "exception": null
    },
    {
      "timestamp": "2025-09-02T02:10:42.143219",
      "level": "INFO",
      "message": "线程3日志5",
      "module": "thread_3",
      "function": "",
      "line": 0,
      "thread_id": "128036",
      "task_id": null,
      "user_id": null,
      "context": null,
      "exception": null
    },
    {
      "timestamp": "2025-09-02T02:10:42.143555",
      "level": "INFO",
      "message": "线程4日志6",
      "module": "thread_4",
      "function": "",
      "line": 0,
      "thread_id": "34996",
      "task_id": null,
      "user_id": null,
      "context": null,
      "exception": null
    },
    {
      "timestamp": "2025-09-02T02:10:42.143666",
      "level": "INFO",
      "message": "线程1日志7",
      "module": "thread_1",
      "function": "",
      "line": 0,
      "thread_id": "122196",
      "task_id": null,
      "user_id": null,
      "context": null,
      "exception": null
    },
    {
      "timestamp": "2025-09-02T02:10:42.143898",
      "level": "INFO",
      "message": "线程2日志6",
      "module": "thread_2",
      "function": "",
      "line": 0,
      "thread_id": "141444",
      "task_id": null,
      "user_id": null,
      "context": null,
      "exception": null
    },
    {
      "timestamp": "2025-09-02T02:10:42.144042",
      "level": "INFO",
      "message": "线程0日志7",
      "module": "thread_0",
      "function": "",
      "line": 0,
      "thread_id": "94620",
      "task_id": null,
      "user_id": null,
      "context": null,
      "exception": null
    },
    {
      "timestamp": "2025-09-02T02:10:42.144113",
      "level": "INFO",
      "message": "线程3日志6",
      "module": "thread_3",
      "function": "",
      "line": 0,
      "thread_id": "128036",
      "task_id": null,
      "user_id": null,
      "context": null,
      "exception": null
    },
    {
      "timestamp": "2025-09-02T02:10:42.144318",
      "level": "INFO",
      "message": "线程1日志8",
      "module": "thread_1",
      "function": "",
      "line": 0,
      "thread_id": "122196",
      "task_id": null,
      "user_id": null,
      "context": null,
      "exception": null
    },
    {
      "timestamp": "2025-09-02T02:10:42.144439",
      "level": "INFO",
      "message": "线程4日志7",
      "module": "thread_4",
      "function": "",
      "line": 0,
      "thread_id": "34996",
      "task_id": null,
      "user_id": null,
      "context": null,
      "exception": null
    },
    {
      "timestamp": "2025-09-02T02:10:42.144544",
      "level": "INFO",
      "message": "线程0日志8",
      "module": "thread_0",
      "function": "",
      "line": 0,
      "thread_id": "94620",
      "task_id": null,
      "user_id": null,
      "context": null,
      "exception": null
    },
    {
      "timestamp": "2025-09-02T02:10:42.144727",
      "level": "INFO",
      "message": "线程3日志7",
      "module": "thread_3",
      "function": "",
      "line": 0,
      "thread_id": "128036",
      "task_id": null,
      "user_id": null,
      "context": null,
      "exception": null
    },
    {
      "timestamp": "2025-09-02T02:10:42.144921",
      "level": "INFO",
      "message": "线程1日志9",
      "module": "thread_1",
      "function": "",
      "line": 0,
      "thread_id": "122196",
      "task_id": null,
      "user_id": null,
      "context": null,
      "exception": null
    },
    {
      "timestamp": "2025-09-02T02:10:42.145088",
      "level": "INFO",
      "message": "线程2日志7",
      "module": "thread_2",
      "function": "",
      "line": 0,
      "thread_id": "141444",
      "task_id": null,
      "user_id": null,
      "context": null,
      "exception": null
    },
    {
      "timestamp": "2025-09-02T02:10:42.145280",
      "level": "INFO",
      "message": "线程0日志9",
      "module": "thread_0",
      "function": "",
      "line": 0,
      "thread_id": "94620",
      "task_id": null,
      "user_id": null,
      "context": null,
      "exception": null
    },
    {
      "timestamp": "2025-09-02T02:10:42.145399",
      "level": "INFO",
      "message": "线程3日志8",
      "module": "thread_3",
      "function": "",
      "line": 0,
      "thread_id": "128036",
      "task_id": null,
      "user_id": null,
      "context": null,
      "exception": null
    },
    {
      "timestamp": "2025-09-02T02:10:42.145479",
      "level": "INFO",
      "message": "线程4日志8",
      "module": "thread_4",
      "function": "",
      "line": 0,
      "thread_id": "34996",
      "task_id": null,
      "user_id": null,
      "context": null,
      "exception": null
    },
    {
      "timestamp": "2025-09-02T02:10:42.145666",
      "level": "INFO",
      "message": "线程1日志10",
      "module": "thread_1",
      "function": "",
      "line": 0,
      "thread_id": "122196",
      "task_id": null,
      "user_id": null,
      "context": null,
      "exception": null
    },
    {
      "timestamp": "2025-09-02T02:10:42.145843",
      "level": "INFO",
      "message": "线程2日志8",
      "module": "thread_2",
      "function": "",
      "line": 0,
      "thread_id": "141444",
      "task_id": null,
      "user_id": null,
      "context": null,
      "exception": null
    },
    {
      "timestamp": "2025-09-02T02:10:42.146096",
      "level": "INFO",
      "message": "线程4日志9",
      "module": "thread_4",
      "function": "",
      "line": 0,
      "thread_id": "34996",
      "task_id": null,
      "user_id": null,
      "context": null,
      "exception": null
    },
    {
      "timestamp": "2025-09-02T02:10:42.146178",
      "level": "INFO",
      "message": "线程0日志10",
      "module": "thread_0",
      "function": "",
      "line": 0,
      "thread_id": "94620",
      "task_id": null,
      "user_id": null,
      "context": null,
      "exception": null
    },
    {
      "timestamp": "2025-09-02T02:10:42.146322",
      "level": "INFO",
      "message": "线程3日志9",
      "module": "thread_3",
      "function": "",
      "line": 0,
      "thread_id": "128036",
      "task_id": null,
      "user_id": null,
      "context": null,
      "exception": null
    },
    {
      "timestamp": "2025-09-02T02:10:42.146397",
      "level": "INFO",
      "message": "线程1日志11",
      "module": "thread_1",
      "function": "",
      "line": 0,
      "thread_id": "122196",
      "task_id": null,
      "user_id": null,
      "context": null,
      "exception": null
    },
    {
      "timestamp": "2025-09-02T02:10:42.146546",
      "level": "INFO",
      "message": "线程2日志9",
      "module": "thread_2",
      "function": "",
      "line": 0,
      "thread_id": "141444",
      "task_id": null,
      "user_id": null,
      "context": null,
      "exception": null
    },
    {
      "timestamp": "2025-09-02T02:10:42.146682",
      "level": "INFO",
      "message": "线程4日志10",
      "module": "thread_4",
      "function": "",
      "line": 0,
      "thread_id": "34996",
      "task_id": null,
      "user_id": null,
      "context": null,
      "exception": null
    },
    {
      "timestamp": "2025-09-02T02:10:42.146882",
      "level": "INFO",
      "message": "线程1日志12",
      "module": "thread_1",
      "function": "",
      "line": 0,
      "thread_id": "122196",
      "task_id": null,
      "user_id": null,
      "context": null,
      "exception": null
    },
    {
      "timestamp": "2025-09-02T02:10:42.147063",
      "level": "INFO",
      "message": "线程0日志11",
      "module": "thread_0",
      "function": "",
      "line": 0,
      "thread_id": "94620",
      "task_id": null,
      "user_id": null,
      "context": null,
      "exception": null
    },
    {
      "timestamp": "2025-09-02T02:10:42.147311",
      "level": "INFO",
      "message": "线程3日志10",
      "module": "thread_3",
      "function": "",
      "line": 0,
      "thread_id": "128036",
      "task_id": null,
      "user_id": null,
      "context": null,
      "exception": null
    },
    {
      "timestamp": "2025-09-02T02:10:42.147447",
      "level": "INFO",
      "message": "线程4日志11",
      "module": "thread_4",
      "function": "",
      "line": 0,
      "thread_id": "34996",
      "task_id": null,
      "user_id": null,
      "context": null,
      "exception": null
    },
    {
      "timestamp": "2025-09-02T02:10:42.147532",
      "level": "INFO",
      "message": "线程2日志10",
      "module": "thread_2",
      "function": "",
      "line": 0,
      "thread_id": "141444",
      "task_id": null,
      "user_id": null,
      "context": null,
      "exception": null
    },
    {
      "timestamp": "2025-09-02T02:10:42.147713",
      "level": "INFO",
      "message": "线程1日志13",
      "module": "thread_1",
      "function": "",
      "line": 0,
      "thread_id": "122196",
      "task_id": null,
      "user_id": null,
      "context": null,
      "exception": null
    },
    {
      "timestamp": "2025-09-02T02:10:42.148073",
      "level": "INFO",
      "message": "线程0日志12",
      "module": "thread_0",
      "function": "",
      "line": 0,
      "thread_id": "94620",
      "task_id": null,
      "user_id": null,
      "context": null,
      "exception": null
    },
    {
      "timestamp": "2025-09-02T02:10:42.148128",
      "level": "INFO",
      "message": "线程4日志12",
      "module": "thread_4",
      "function": "",
      "line": 0,
      "thread_id": "34996",
      "task_id": null,
      "user_id": null,
      "context": null,
      "exception": null
    },
    {
      "timestamp": "2025-09-02T02:10:42.148186",
      "level": "INFO",
      "message": "线程3日志11",
      "module": "thread_3",
      "function": "",
      "line": 0,
      "thread_id": "128036",
      "task_id": null,
      "user_id": null,
      "context": null,
      "exception": null
    },
    {
      "timestamp": "2025-09-02T02:10:42.148263",
      "level": "INFO",
      "message": "线程2日志11",
      "module": "thread_2",
      "function": "",
      "line": 0,
      "thread_id": "141444",
      "task_id": null,
      "user_id": null,
      "context": null,
      "exception": null
    },
    {
      "timestamp": "2025-09-02T02:10:42.148407",
      "level": "INFO",
      "message": "线程1日志14",
      "module": "thread_1",
      "function": "",
      "line": 0,
      "thread_id": "122196",
      "task_id": null,
      "user_id": null,
      "context": null,
      "exception": null
    },
    {
      "timestamp": "2025-09-02T02:10:42.148655",
      "level": "INFO",
      "message": "线程0日志13",
      "module": "thread_0",
      "function": "",
      "line": 0,
      "thread_id": "94620",
      "task_id": null,
      "user_id": null,
      "context": null,
      "exception": null
    },
    {
      "timestamp": "2025-09-02T02:10:42.148894",
      "level": "INFO",
      "message": "线程4日志13",
      "module": "thread_4",
      "function": "",
      "line": 0,
      "thread_id": "34996",
      "task_id": null,
      "user_id": null,
      "context": null,
      "exception": null
    },
    {
      "timestamp": "2025-09-02T02:10:42.148950",
      "level": "INFO",
      "message": "线程3日志12",
      "module": "thread_3",
      "function": "",
      "line": 0,
      "thread_id": "128036",
      "task_id": null,
      "user_id": null,
      "context": null,
      "exception": null
    },
    {
      "timestamp": "2025-09-02T02:10:42.149014",
      "level": "INFO",
      "message": "线程2日志12",
      "module": "thread_2",
      "function": "",
      "line": 0,
      "thread_id": "141444",
      "task_id": null,
      "user_id": null,
      "context": null,
      "exception": null
    },
    {
      "timestamp": "2025-09-02T02:10:42.149161",
      "level": "INFO",
      "message": "线程1日志15",
      "module": "thread_1",
      "function": "",
      "line": 0,
      "thread_id": "122196",
      "task_id": null,
      "user_id": null,
      "context": null,
      "exception": null
    },
    {
      "timestamp": "2025-09-02T02:10:42.149320",
      "level": "INFO",
      "message": "线程0日志14",
      "module": "thread_0",
      "function": "",
      "line": 0,
      "thread_id": "94620",
      "task_id": null,
      "user_id": null,
      "context": null,
      "exception": null
    },
    {
      "timestamp": "2025-09-02T02:10:42.149480",
      "level": "INFO",
      "message": "线程3日志13",
      "module": "thread_3",
      "function": "",
      "line": 0,
      "thread_id": "128036",
      "task_id": null,
      "user_id": null,
      "context": null,
      "exception": null
    },
    {
      "timestamp": "2025-09-02T02:10:42.149555",
      "level": "INFO",
      "message": "线程2日志13",
      "module": "thread_2",
      "function": "",
      "line": 0,
      "thread_id": "141444",
      "task_id": null,
      "user_id": null,
      "context": null,
      "exception": null
    },
    {
      "timestamp": "2025-09-02T02:10:42.149687",
      "level": "INFO",
      "message": "线程4日志14",
      "module": "thread_4",
      "function": "",
      "line": 0,
      "thread_id": "34996",
      "task_id": null,
      "user_id": null,
      "context": null,
      "exception": null
    },
    {
      "timestamp": "2025-09-02T02:10:42.149804",
      "level": "INFO",
      "message": "线程1日志16",
      "module": "thread_1",
      "function": "",
      "line": 0,
      "thread_id": "122196",
      "task_id": null,
      "user_id": null,
      "context": null,
      "exception": null
    },
    {
      "timestamp": "2025-09-02T02:10:42.149902",
      "level": "INFO",
      "message": "线程0日志15",
      "module": "thread_0",
      "function": "",
      "line": 0,
      "thread_id": "94620",
      "task_id": null,
      "user_id": null,
      "context": null,
      "exception": null
    },
    {
      "timestamp": "2025-09-02T02:10:42.150030",
      "level": "INFO",
      "message": "线程3日志14",
      "module": "thread_3",
      "function": "",
      "line": 0,
      "thread_id": "128036",
      "task_id": null,
      "user_id": null,
      "context": null,
      "exception": null
    },
    {
      "timestamp": "2025-09-02T02:10:42.150162",
      "level": "INFO",
      "message": "线程4日志15",
      "module": "thread_4",
      "function": "",
      "line": 0,
      "thread_id": "34996",
      "task_id": null,
      "user_id": null,
      "context": null,
      "exception": null
    },
    {
      "timestamp": "2025-09-02T02:10:42.150313",
      "level": "INFO",
      "message": "线程1日志17",
      "module": "thread_1",
      "function": "",
      "line": 0,
      "thread_id": "122196",
      "task_id": null,
      "user_id": null,
      "context": null,
      "exception": null
    },
    {
      "timestamp": "2025-09-02T02:10:42.150548",
      "level": "INFO",
      "message": "线程2日志14",
      "module": "thread_2",
      "function": "",
      "line": 0,
      "thread_id": "141444",
      "task_id": null,
      "user_id": null,
      "context": null,
      "exception": null
    },
    {
      "timestamp": "2025-09-02T02:10:42.150651",
      "level": "INFO",
      "message": "线程0日志16",
      "module": "thread_0",
      "function": "",
      "line": 0,
      "thread_id": "94620",
      "task_id": null,
      "user_id": null,
      "context": null,
      "exception": null
    },
    {
      "timestamp": "2025-09-02T02:10:42.150926",
      "level": "INFO",
      "message": "线程4日志16",
      "module": "thread_4",
      "function": "",
      "line": 0,
      "thread_id": "34996",
      "task_id": null,
      "user_id": null,
      "context": null,
      "exception": null
    },
    {
      "timestamp": "2025-09-02T02:10:42.151004",
      "level": "INFO",
      "message": "线程3日志15",
      "module": "thread_3",
      "function": "",
      "line": 0,
      "thread_id": "128036",
      "task_id": null,
      "user_id": null,
      "context": null,
      "exception": null
    },
    {
      "timestamp": "2025-09-02T02:10:42.151081",
      "level": "INFO",
      "message": "线程1日志18",
      "module": "thread_1",
      "function": "",
      "line": 0,
      "thread_id": "122196",
      "task_id": null,
      "user_id": null,
      "context": null,
      "exception": null
    },
    {
      "timestamp": "2025-09-02T02:10:42.151254",
      "level": "INFO",
      "message": "线程4日志17",
      "module": "thread_4",
      "function": "",
      "line": 0,
      "thread_id": "34996",
      "task_id": null,
      "user_id": null,
      "context": null,
      "exception": null
    },
    {
      "timestamp": "2025-09-02T02:10:42.151618",
      "level": "INFO",
      "message": "线程2日志15",
      "module": "thread_2",
      "function": "",
      "line": 0,
      "thread_id": "141444",
      "task_id": null,
      "user_id": null,
      "context": null,
      "exception": null
    },
    {
      "timestamp": "2025-09-02T02:10:42.151720",
      "level": "INFO",
      "message": "线程4日志18",
      "module": "thread_4",
      "function": "",
      "line": 0,
      "thread_id": "34996",
      "task_id": null,
      "user_id": null,
      "context": null,
      "exception": null
    },
    {
      "timestamp": "2025-09-02T02:10:42.151770",
      "level": "INFO",
      "message": "线程3日志16",
      "module": "thread_3",
      "function": "",
      "line": 0,
      "thread_id": "128036",
      "task_id": null,
      "user_id": null,
      "context": null,
      "exception": null
    },
    {
      "timestamp": "2025-09-02T02:10:42.151829",
      "level": "INFO",
      "message": "线程0日志17",
      "module": "thread_0",
      "function": "",
      "line": 0,
      "thread_id": "94620",
      "task_id": null,
      "user_id": null,
      "context": null,
      "exception": null
    },
    {
      "timestamp": "2025-09-02T02:10:42.151895",
      "level": "INFO",
      "message": "线程1日志19",
      "module": "thread_1",
      "function": "",
      "line": 0,
      "thread_id": "122196",
      "task_id": null,
      "user_id": null,
      "context": null,
      "exception": null
    },
    {
      "timestamp": "2025-09-02T02:10:42.152252",
      "level": "INFO",
      "message": "线程2日志16",
      "module": "thread_2",
      "function": "",
      "line": 0,
      "thread_id": "141444",
      "task_id": null,
      "user_id": null,
      "context": null,
      "exception": null
    },
    {
      "timestamp": "2025-09-02T02:10:42.152306",
      "level": "INFO",
      "message": "线程0日志18",
      "module": "thread_0",
      "function": "",
      "line": 0,
      "thread_id": "94620",
      "task_id": null,
      "user_id": null,
      "context": null,
      "exception": null
    },
    {
      "timestamp": "2025-09-02T02:10:42.152365",
      "level": "INFO",
      "message": "线程4日志19",
      "module": "thread_4",
      "function": "",
      "line": 0,
      "thread_id": "34996",
      "task_id": null,
      "user_id": null,
      "context": null,
      "exception": null
    },
    {
      "timestamp": "2025-09-02T02:10:42.152439",
      "level": "INFO",
      "message": "线程3日志17",
      "module": "thread_3",
      "function": "",
      "line": 0,
      "thread_id": "128036",
      "task_id": null,
      "user_id": null,
      "context": null,
      "exception": null
    },
    {
      "timestamp": "2025-09-02T02:10:42.152597",
      "level": "INFO",
      "message": "线程2日志17",
      "module": "thread_2",
      "function": "",
      "line": 0,
      "thread_id": "141444",
      "task_id": null,
      "user_id": null,
      "context": null,
      "exception": null
    },
    {
      "timestamp": "2025-09-02T02:10:42.152749",
      "level": "INFO",
      "message": "线程0日志19",
      "module": "thread_0",
      "function": "",
      "line": 0,
      "thread_id": "94620",
      "task_id": null,
      "user_id": null,
      "context": null,
      "exception": null
    },
    {
      "timestamp": "2025-09-02T02:10:42.152893",
      "level": "INFO",
      "message": "线程1日志20",
      "module": "thread_1",
      "function": "",
      "line": 0,
      "thread_id": "122196",
      "task_id": null,
      "user_id": null,
      "context": null,
      "exception": null
    },
    {
      "timestamp": "2025-09-02T02:10:42.153031",
      "level": "INFO",
      "message": "线程3日志18",
      "module": "thread_3",
      "function": "",
      "line": 0,
      "thread_id": "128036",
      "task_id": null,
      "user_id": null,
      "context": null,
      "exception": null
    },
    {
      "timestamp": "2025-09-02T02:10:42.153166",
      "level": "INFO",
      "message": "线程4日志20",
      "module": "thread_4",
      "function": "",
      "line": 0,
      "thread_id": "34996",
      "task_id": null,
      "user_id": null,
      "context": null,
      "exception": null
    },
    {
      "timestamp": "2025-09-02T02:10:42.153432",
      "level": "INFO",
      "message": "线程2日志18",
      "module": "thread_2",
      "function": "",
      "line": 0,
      "thread_id": "141444",
      "task_id": null,
      "user_id": null,
      "context": null,
      "exception": null
    },
    {
      "timestamp": "2025-09-02T02:10:42.153535",
      "level": "INFO",
      "message": "线程3日志19",
      "module": "thread_3",
      "function": "",
      "line": 0,
      "thread_id": "128036",
      "task_id": null,
      "user_id": null,
      "context": null,
      "exception": null
    },
    {
      "timestamp": "2025-09-02T02:10:42.153891",
      "level": "INFO",
      "message": "线程4日志21",
      "module": "thread_4",
      "function": "",
      "line": 0,
      "thread_id": "34996",
      "task_id": null,
      "user_id": null,
      "context": null,
      "exception": null
    },
    {
      "timestamp": "2025-09-02T02:10:42.154005",
      "level": "INFO",
      "message": "线程0日志20",
      "module": "thread_0",
      "function": "",
      "line": 0,
      "thread_id": "94620",
      "task_id": null,
      "user_id": null,
      "context": null,
      "exception": null
    },
    {
      "timestamp": "2025-09-02T02:10:42.154088",
      "level": "INFO",
      "message": "线程1日志21",
      "module": "thread_1",
      "function": "",
      "line": 0,
      "thread_id": "122196",
      "task_id": null,
      "user_id": null,
      "context": null,
      "exception": null
    },
    {
      "timestamp": "2025-09-02T02:10:42.154320",
      "level": "INFO",
      "message": "线程3日志20",
      "module": "thread_3",
      "function": "",
      "line": 0,
      "thread_id": "128036",
      "task_id": null,
      "user_id": null,
      "context": null,
      "exception": null
    },
    {
      "timestamp": "2025-09-02T02:10:42.154527",
      "level": "INFO",
      "message": "线程2日志19",
      "module": "thread_2",
      "function": "",
      "line": 0,
      "thread_id": "141444",
      "task_id": null,
      "user_id": null,
      "context": null,
      "exception": null
    },
    {
      "timestamp": "2025-09-02T02:10:42.154619",
      "level": "INFO",
      "message": "线程4日志22",
      "module": "thread_4",
      "function": "",
      "line": 0,
      "thread_id": "34996",
      "task_id": null,
      "user_id": null,
      "context": null,
      "exception": null
    },
    {
      "timestamp": "2025-09-02T02:10:42.154815",
      "level": "INFO",
      "message": "线程1日志22",
      "module": "thread_1",
      "function": "",
      "line": 0,
      "thread_id": "122196",
      "task_id": null,
      "user_id": null,
      "context": null,
      "exception": null
    },
    {
      "timestamp": "2025-09-02T02:10:42.155108",
      "level": "INFO",
      "message": "线程0日志21",
      "module": "thread_0",
      "function": "",
      "line": 0,
      "thread_id": "94620",
      "task_id": null,
      "user_id": null,
      "context": null,
      "exception": null
    },
    {
      "timestamp": "2025-09-02T02:10:42.155246",
      "level": "INFO",
      "message": "线程2日志20",
      "module": "thread_2",
      "function": "",
      "line": 0,
      "thread_id": "141444",
      "task_id": null,
      "user_id": null,
      "context": null,
      "exception": null
    },
    {
      "timestamp": "2025-09-02T02:10:42.155331",
      "level": "INFO",
      "message": "线程3日志21",
      "module": "thread_3",
      "function": "",
      "line": 0,
      "thread_id": "128036",
      "task_id": null,
      "user_id": null,
      "context": null,
      "exception": null
    },
    {
      "timestamp": "2025-09-02T02:10:42.155523",
      "level": "INFO",
      "message": "线程1日志23",
      "module": "thread_1",
      "function": "",
      "line": 0,
      "thread_id": "122196",
      "task_id": null,
      "user_id": null,
      "context": null,
      "exception": null
    },
    {
      "timestamp": "2025-09-02T02:10:42.155749",
      "level": "INFO",
      "message": "线程4日志23",
      "module": "thread_4",
      "function": "",
      "line": 0,
      "thread_id": "34996",
      "task_id": null,
      "user_id": null,
      "context": null,
      "exception": null
    },
    {
      "timestamp": "2025-09-02T02:10:42.155975",
      "level": "INFO",
      "message": "线程0日志22",
      "module": "thread_0",
      "function": "",
      "line": 0,
      "thread_id": "94620",
      "task_id": null,
      "user_id": null,
      "context": null,
      "exception": null
    },
    {
      "timestamp": "2025-09-02T02:10:42.156182",
      "level": "INFO",
      "message": "线程2日志21",
      "module": "thread_2",
      "function": "",
      "line": 0,
      "thread_id": "141444",
      "task_id": null,
      "user_id": null,
      "context": null,
      "exception": null
    },
    {
      "timestamp": "2025-09-02T02:10:42.156369",
      "level": "INFO",
      "message": "线程3日志22",
      "module": "thread_3",
      "function": "",
      "line": 0,
      "thread_id": "128036",
      "task_id": null,
      "user_id": null,
      "context": null,
      "exception": null
    },
    {
      "timestamp": "2025-09-02T02:10:42.156627",
      "level": "INFO",
      "message": "线程1日志24",
      "module": "thread_1",
      "function": "",
      "line": 0,
      "thread_id": "122196",
      "task_id": null,
      "user_id": null,
      "context": null,
      "exception": null
    },
    {
      "timestamp": "2025-09-02T02:10:42.156736",
      "level": "INFO",
      "message": "线程4日志24",
      "module": "thread_4",
      "function": "",
      "line": 0,
      "thread_id": "34996",
      "task_id": null,
      "user_id": null,
      "context": null,
      "exception": null
    },
    {
      "timestamp": "2025-09-02T02:10:42.156939",
      "level": "INFO",
      "message": "线程2日志22",
      "module": "thread_2",
      "function": "",
      "line": 0,
      "thread_id": "141444",
      "task_id": null,
      "user_id": null,
      "context": null,
      "exception": null
    },
    {
      "timestamp": "2025-09-02T02:10:42.157102",
      "level": "INFO",
      "message": "线程0日志23",
      "module": "thread_0",
      "function": "",
      "line": 0,
      "thread_id": "94620",
      "task_id": null,
      "user_id": null,
      "context": null,
      "exception": null
    },
    {
      "timestamp": "2025-09-02T02:10:42.157248",
      "level": "INFO",
      "message": "线程3日志23",
      "module": "thread_3",
      "function": "",
      "line": 0,
      "thread_id": "128036",
      "task_id": null,
      "user_id": null,
      "context": null,
      "exception": null
    },
    {
      "timestamp": "2025-09-02T02:10:42.157435",
      "level": "INFO",
      "message": "线程4日志25",
      "module": "thread_4",
      "function": "",
      "line": 0,
      "thread_id": "34996",
      "task_id": null,
      "user_id": null,
      "context": null,
      "exception": null
    },
    {
      "timestamp": "2025-09-02T02:10:42.157970",
      "level": "INFO",
      "message": "线程1日志25",
      "module": "thread_1",
      "function": "",
      "line": 0,
      "thread_id": "122196",
      "task_id": null,
      "user_id": null,
      "context": null,
      "exception": null
    },
    {
      "timestamp": "2025-09-02T02:10:42.158261",
      "level": "INFO",
      "message": "线程2日志23",
      "module": "thread_2",
      "function": "",
      "line": 0,
      "thread_id": "141444",
      "task_id": null,
      "user_id": null,
      "context": null,
      "exception": null
    },
    {
      "timestamp": "2025-09-02T02:10:42.158498",
      "level": "INFO",
      "message": "线程3日志24",
      "module": "thread_3",
      "function": "",
      "line": 0,
      "thread_id": "128036",
      "task_id": null,
      "user_id": null,
      "context": null,
      "exception": null
    },
    {
      "timestamp": "2025-09-02T02:10:42.158595",
      "level": "INFO",
      "message": "线程0日志24",
      "module": "thread_0",
      "function": "",
      "line": 0,
      "thread_id": "94620",
      "task_id": null,
      "user_id": null,
      "context": null,
      "exception": null
    },
    {
      "timestamp": "2025-09-02T02:10:42.158717",
      "level": "INFO",
      "message": "线程4日志26",
      "module": "thread_4",
      "function": "",
      "line": 0,
      "thread_id": "34996",
      "task_id": null,
      "user_id": null,
      "context": null,
      "exception": null
    },
    {
      "timestamp": "2025-09-02T02:10:42.158875",
      "level": "INFO",
      "message": "线程1日志26",
      "module": "thread_1",
      "function": "",
      "line": 0,
      "thread_id": "122196",
      "task_id": null,
      "user_id": null,
      "context": null,
      "exception": null
    },
    {
      "timestamp": "2025-09-02T02:10:42.159238",
      "level": "INFO",
      "message": "线程3日志25",
      "module": "thread_3",
      "function": "",
      "line": 0,
      "thread_id": "128036",
      "task_id": null,
      "user_id": null,
      "context": null,
      "exception": null
    },
    {
      "timestamp": "2025-09-02T02:10:42.159338",
      "level": "INFO",
      "message": "线程2日志24",
      "module": "thread_2",
      "function": "",
      "line": 0,
      "thread_id": "141444",
      "task_id": null,
      "user_id": null,
      "context": null,
      "exception": null
    },
    {
      "timestamp": "2025-09-02T02:10:42.159624",
      "level": "INFO",
      "message": "线程0日志25",
      "module": "thread_0",
      "function": "",
      "line": 0,
      "thread_id": "94620",
      "task_id": null,
      "user_id": null,
      "context": null,
      "exception": null
    },
    {
      "timestamp": "2025-09-02T02:10:42.159699",
      "level": "INFO",
      "message": "线程4日志27",
      "module": "thread_4",
      "function": "",
      "line": 0,
      "thread_id": "34996",
      "task_id": null,
      "user_id": null,
      "context": null,
      "exception": null
    },
    {
      "timestamp": "2025-09-02T02:10:42.159771",
      "level": "INFO",
      "message": "线程1日志27",
      "module": "thread_1",
      "function": "",
      "line": 0,
      "thread_id": "122196",
      "task_id": null,
      "user_id": null,
      "context": null,
      "exception": null
    },
    {
      "timestamp": "2025-09-02T02:10:42.160126",
      "level": "INFO",
      "message": "线程0日志26",
      "module": "thread_0",
      "function": "",
      "line": 0,
      "thread_id": "94620",
      "task_id": null,
      "user_id": null,
      "context": null,
      "exception": null
    },
    {
      "timestamp": "2025-09-02T02:10:42.160296",
      "level": "INFO",
      "message": "线程3日志26",
      "module": "thread_3",
      "function": "",
      "line": 0,
      "thread_id": "128036",
      "task_id": null,
      "user_id": null,
      "context": null,
      "exception": null
    },
    {
      "timestamp": "2025-09-02T02:10:42.160684",
      "level": "INFO",
      "message": "线程2日志25",
      "module": "thread_2",
      "function": "",
      "line": 0,
      "thread_id": "141444",
      "task_id": null,
      "user_id": null,
      "context": null,
      "exception": null
    },
    {
      "timestamp": "2025-09-02T02:10:42.160767",
      "level": "INFO",
      "message": "线程4日志28",
      "module": "thread_4",
      "function": "",
      "line": 0,
      "thread_id": "34996",
      "task_id": null,
      "user_id": null,
      "context": null,
      "exception": null
    },
    {
      "timestamp": "2025-09-02T02:10:42.160866",
      "level": "INFO",
      "message": "线程1日志28",
      "module": "thread_1",
      "function": "",
      "line": 0,
      "thread_id": "122196",
      "task_id": null,
      "user_id": null,
      "context": null,
      "exception": null
    },
    {
      "timestamp": "2025-09-02T02:10:42.161074",
      "level": "INFO",
      "message": "线程0日志27",
      "module": "thread_0",
      "function": "",
      "line": 0,
      "thread_id": "94620",
      "task_id": null,
      "user_id": null,
      "context": null,
      "exception": null
    },
    {
      "timestamp": "2025-09-02T02:10:42.161224",
      "level": "INFO",
      "message": "线程3日志27",
      "module": "thread_3",
      "function": "",
      "line": 0,
      "thread_id": "128036",
      "task_id": null,
      "user_id": null,
      "context": null,
      "exception": null
    },
    {
      "timestamp": "2025-09-02T02:10:42.161321",
      "level": "INFO",
      "message": "线程2日志26",
      "module": "thread_2",
      "function": "",
      "line": 0,
      "thread_id": "141444",
      "task_id": null,
      "user_id": null,
      "context": null,
      "exception": null
    },
    {
      "timestamp": "2025-09-02T02:10:42.161399",
      "level": "INFO",
      "message": "线程4日志29",
      "module": "thread_4",
      "function": "",
      "line": 0,
      "thread_id": "34996",
      "task_id": null,
      "user_id": null,
      "context": null,
      "exception": null
    },
    {
      "timestamp": "2025-09-02T02:10:42.161568",
      "level": "INFO",
      "message": "线程1日志29",
      "module": "thread_1",
      "function": "",
      "line": 0,
      "thread_id": "122196",
      "task_id": null,
      "user_id": null,
      "context": null,
      "exception": null
    },
    {
      "timestamp": "2025-09-02T02:10:42.161768",
      "level": "INFO",
      "message": "线程3日志28",
      "module": "thread_3",
      "function": "",
      "line": 0,
      "thread_id": "128036",
      "task_id": null,
      "user_id": null,
      "context": null,
      "exception": null
    },
    {
      "timestamp": "2025-09-02T02:10:42.161967",
      "level": "INFO",
      "message": "线程0日志28",
      "module": "thread_0",
      "function": "",
      "line": 0,
      "thread_id": "94620",
      "task_id": null,
      "user_id": null,
      "context": null,
      "exception": null
    },
    {
      "timestamp": "2025-09-02T02:10:42.162113",
      "level": "INFO",
      "message": "线程4日志30",
      "module": "thread_4",
      "function": "",
      "line": 0,
      "thread_id": "34996",
      "task_id": null,
      "user_id": null,
      "context": null,
      "exception": null
    },
    {
      "timestamp": "2025-09-02T02:10:42.162211",
      "level": "INFO",
      "message": "线程2日志27",
      "module": "thread_2",
      "function": "",
      "line": 0,
      "thread_id": "141444",
      "task_id": null,
      "user_id": null,
      "context": null,
      "exception": null
    },
    {
      "timestamp": "2025-09-02T02:10:42.162377",
      "level": "INFO",
      "message": "线程1日志30",
      "module": "thread_1",
      "function": "",
      "line": 0,
      "thread_id": "122196",
      "task_id": null,
      "user_id": null,
      "context": null,
      "exception": null
    },
    {
      "timestamp": "2025-09-02T02:10:42.162517",
      "level": "INFO",
      "message": "线程0日志29",
      "module": "thread_0",
      "function": "",
      "line": 0,
      "thread_id": "94620",
      "task_id": null,
      "user_id": null,
      "context": null,
      "exception": null
    },
    {
      "timestamp": "2025-09-02T02:10:42.162667",
      "level": "INFO",
      "message": "线程4日志31",
      "module": "thread_4",
      "function": "",
      "line": 0,
      "thread_id": "34996",
      "task_id": null,
      "user_id": null,
      "context": null,
      "exception": null
    },
    {
      "timestamp": "2025-09-02T02:10:42.162816",
      "level": "INFO",
      "message": "线程2日志28",
      "module": "thread_2",
      "function": "",
      "line": 0,
      "thread_id": "141444",
      "task_id": null,
      "user_id": null,
      "context": null,
      "exception": null
    },
    {
      "timestamp": "2025-09-02T02:10:42.162966",
      "level": "INFO",
      "message": "线程3日志29",
      "module": "thread_3",
      "function": "",
      "line": 0,
      "thread_id": "128036",
      "task_id": null,
      "user_id": null,
      "context": null,
      "exception": null
    },
    {
      "timestamp": "2025-09-02T02:10:42.163227",
      "level": "INFO",
      "message": "线程0日志30",
      "module": "thread_0",
      "function": "",
      "line": 0,
      "thread_id": "94620",
      "task_id": null,
      "user_id": null,
      "context": null,
      "exception": null
    },
    {
      "timestamp": "2025-09-02T02:10:42.163387",
      "level": "INFO",
      "message": "线程1日志31",
      "module": "thread_1",
      "function": "",
      "line": 0,
      "thread_id": "122196",
      "task_id": null,
      "user_id": null,
      "context": null,
      "exception": null
    },
    {
      "timestamp": "2025-09-02T02:10:42.163481",
      "level": "INFO",
      "message": "线程2日志29",
      "module": "thread_2",
      "function": "",
      "line": 0,
      "thread_id": "141444",
      "task_id": null,
      "user_id": null,
      "context": null,
      "exception": null
    },
    {
      "timestamp": "2025-09-02T02:10:42.163608",
      "level": "INFO",
      "message": "线程4日志32",
      "module": "thread_4",
      "function": "",
      "line": 0,
      "thread_id": "34996",
      "task_id": null,
      "user_id": null,
      "context": null,
      "exception": null
    },
    {
      "timestamp": "2025-09-02T02:10:42.163757",
      "level": "INFO",
      "message": "线程0日志31",
      "module": "thread_0",
      "function": "",
      "line": 0,
      "thread_id": "94620",
      "task_id": null,
      "user_id": null,
      "context": null,
      "exception": null
    },
    {
      "timestamp": "2025-09-02T02:10:42.163924",
      "level": "INFO",
      "message": "线程1日志32",
      "module": "thread_1",
      "function": "",
      "line": 0,
      "thread_id": "122196",
      "task_id": null,
      "user_id": null,
      "context": null,
      "exception": null
    },
    {
      "timestamp": "2025-09-02T02:10:42.164085",
      "level": "INFO",
      "message": "线程3日志30",
      "module": "thread_3",
      "function": "",
      "line": 0,
      "thread_id": "128036",
      "task_id": null,
      "user_id": null,
      "context": null,
      "exception": null
    },
    {
      "timestamp": "2025-09-02T02:10:42.164196",
      "level": "INFO",
      "message": "线程4日志33",
      "module": "thread_4",
      "function": "",
      "line": 0,
      "thread_id": "34996",
      "task_id": null,
      "user_id": null,
      "context": null,
      "exception": null
    },
    {
      "timestamp": "2025-09-02T02:10:42.164293",
      "level": "INFO",
      "message": "线程2日志30",
      "module": "thread_2",
      "function": "",
      "line": 0,
      "thread_id": "141444",
      "task_id": null,
      "user_id": null,
      "context": null,
      "exception": null
    },
    {
      "timestamp": "2025-09-02T02:10:42.164431",
      "level": "INFO",
      "message": "线程0日志32",
      "module": "thread_0",
      "function": "",
      "line": 0,
      "thread_id": "94620",
      "task_id": null,
      "user_id": null,
      "context": null,
      "exception": null
    },
    {
      "timestamp": "2025-09-02T02:10:42.164555",
      "level": "INFO",
      "message": "线程1日志33",
      "module": "thread_1",
      "function": "",
      "line": 0,
      "thread_id": "122196",
      "task_id": null,
      "user_id": null,
      "context": null,
      "exception": null
    },
    {
      "timestamp": "2025-09-02T02:10:42.164754",
      "level": "INFO",
      "message": "线程2日志31",
      "module": "thread_2",
      "function": "",
      "line": 0,
      "thread_id": "141444",
      "task_id": null,
      "user_id": null,
      "context": null,
      "exception": null
    },
    {
      "timestamp": "2025-09-02T02:10:42.165131",
      "level": "INFO",
      "message": "线程4日志34",
      "module": "thread_4",
      "function": "",
      "line": 0,
      "thread_id": "34996",
      "task_id": null,
      "user_id": null,
      "context": null,
      "exception": null
    },
    {
      "timestamp": "2025-09-02T02:10:42.165274",
      "level": "INFO",
      "message": "线程3日志31",
      "module": "thread_3",
      "function": "",
      "line": 0,
      "thread_id": "128036",
      "task_id": null,
      "user_id": null,
      "context": null,
      "exception": null
    },
    {
      "timestamp": "2025-09-02T02:10:42.165345",
      "level": "INFO",
      "message": "线程1日志34",
      "module": "thread_1",
      "function": "",
      "line": 0,
      "thread_id": "122196",
      "task_id": null,
      "user_id": null,
      "context": null,
      "exception": null
    },
    {
      "timestamp": "2025-09-02T02:10:42.165515",
      "level": "INFO",
      "message": "线程0日志33",
      "module": "thread_0",
      "function": "",
      "line": 0,
      "thread_id": "94620",
      "task_id": null,
      "user_id": null,
      "context": null,
      "exception": null
    },
    {
      "timestamp": "2025-09-02T02:10:42.165806",
      "level": "INFO",
      "message": "线程3日志32",
      "module": "thread_3",
      "function": "",
      "line": 0,
      "thread_id": "128036",
      "task_id": null,
      "user_id": null,
      "context": null,
      "exception": null
    },
    {
      "timestamp": "2025-09-02T02:10:42.165946",
      "level": "INFO",
      "message": "线程4日志35",
      "module": "thread_4",
      "function": "",
      "line": 0,
      "thread_id": "34996",
      "task_id": null,
      "user_id": null,
      "context": null,
      "exception": null
    },
    {
      "timestamp": "2025-09-02T02:10:42.166029",
      "level": "INFO",
      "message": "线程1日志35",
      "module": "thread_1",
      "function": "",
      "line": 0,
      "thread_id": "122196",
      "task_id": null,
      "user_id": null,
      "context": null,
      "exception": null
    },
    {
      "timestamp": "2025-09-02T02:10:42.166097",
      "level": "INFO",
      "message": "线程2日志32",
      "module": "thread_2",
      "function": "",
      "line": 0,
      "thread_id": "141444",
      "task_id": null,
      "user_id": null,
      "context": null,
      "exception": null
    },
    {
      "timestamp": "2025-09-02T02:10:42.166231",
      "level": "INFO",
      "message": "线程0日志34",
      "module": "thread_0",
      "function": "",
      "line": 0,
      "thread_id": "94620",
      "task_id": null,
      "user_id": null,
      "context": null,
      "exception": null
    },
    {
      "timestamp": "2025-09-02T02:10:42.166361",
      "level": "INFO",
      "message": "线程4日志36",
      "module": "thread_4",
      "function": "",
      "line": 0,
      "thread_id": "34996",
      "task_id": null,
      "user_id": null,
      "context": null,
      "exception": null
    },
    {
      "timestamp": "2025-09-02T02:10:42.166491",
      "level": "INFO",
      "message": "线程1日志36",
      "module": "thread_1",
      "function": "",
      "line": 0,
      "thread_id": "122196",
      "task_id": null,
      "user_id": null,
      "context": null,
      "exception": null
    },
    {
      "timestamp": "2025-09-02T02:10:42.166633",
      "level": "INFO",
      "message": "线程0日志35",
      "module": "thread_0",
      "function": "",
      "line": 0,
      "thread_id": "94620",
      "task_id": null,
      "user_id": null,
      "context": null,
      "exception": null
    },
    {
      "timestamp": "2025-09-02T02:10:42.166768",
      "level": "INFO",
      "message": "线程2日志33",
      "module": "thread_2",
      "function": "",
      "line": 0,
      "thread_id": "141444",
      "task_id": null,
      "user_id": null,
      "context": null,
      "exception": null
    },
    {
      "timestamp": "2025-09-02T02:10:42.166990",
      "level": "INFO",
      "message": "线程4日志37",
      "module": "thread_4",
      "function": "",
      "line": 0,
      "thread_id": "34996",
      "task_id": null,
      "user_id": null,
      "context": null,
      "exception": null
    },
    {
      "timestamp": "2025-09-02T02:10:42.167146",
      "level": "INFO",
      "message": "线程3日志33",
      "module": "thread_3",
      "function": "",
      "line": 0,
      "thread_id": "128036",
      "task_id": null,
      "user_id": null,
      "context": null,
      "exception": null
    },
    {
      "timestamp": "2025-09-02T02:10:42.167254",
      "level": "INFO",
      "message": "线程0日志36",
      "module": "thread_0",
      "function": "",
      "line": 0,
      "thread_id": "94620",
      "task_id": null,
      "user_id": null,
      "context": null,
      "exception": null
    },
    {
      "timestamp": "2025-09-02T02:10:42.167329",
      "level": "INFO",
      "message": "线程1日志37",
      "module": "thread_1",
      "function": "",
      "line": 0,
      "thread_id": "122196",
      "task_id": null,
      "user_id": null,
      "context": null,
      "exception": null
    },
    {
      "timestamp": "2025-09-02T02:10:42.167451",
      "level": "INFO",
      "message": "线程2日志34",
      "module": "thread_2",
      "function": "",
      "line": 0,
      "thread_id": "141444",
      "task_id": null,
      "user_id": null,
      "context": null,
      "exception": null
    },
    {
      "timestamp": "2025-09-02T02:10:42.167644",
      "level": "INFO",
      "message": "线程4日志38",
      "module": "thread_4",
      "function": "",
      "line": 0,
      "thread_id": "34996",
      "task_id": null,
      "user_id": null,
      "context": null,
      "exception": null
    },
    {
      "timestamp": "2025-09-02T02:10:42.167793",
      "level": "INFO",
      "message": "线程3日志34",
      "module": "thread_3",
      "function": "",
      "line": 0,
      "thread_id": "128036",
      "task_id": null,
      "user_id": null,
      "context": null,
      "exception": null
    },
    {
      "timestamp": "2025-09-02T02:10:42.167960",
      "level": "INFO",
      "message": "线程0日志37",
      "module": "thread_0",
      "function": "",
      "line": 0,
      "thread_id": "94620",
      "task_id": null,
      "user_id": null,
      "context": null,
      "exception": null
    },
    {
      "timestamp": "2025-09-02T02:10:42.168081",
      "level": "INFO",
      "message": "线程1日志38",
      "module": "thread_1",
      "function": "",
      "line": 0,
      "thread_id": "122196",
      "task_id": null,
      "user_id": null,
      "context": null,
      "exception": null
    },
    {
      "timestamp": "2025-09-02T02:10:42.168150",
      "level": "INFO",
      "message": "线程2日志35",
      "module": "thread_2",
      "function": "",
      "line": 0,
      "thread_id": "141444",
      "task_id": null,
      "user_id": null,
      "context": null,
      "exception": null
    },
    {
      "timestamp": "2025-09-02T02:10:42.168384",
      "level": "INFO",
      "message": "线程3日志35",
      "module": "thread_3",
      "function": "",
      "line": 0,
      "thread_id": "128036",
      "task_id": null,
      "user_id": null,
      "context": null,
      "exception": null
    },
    {
      "timestamp": "2025-09-02T02:10:42.168477",
      "level": "INFO",
      "message": "线程4日志39",
      "module": "thread_4",
      "function": "",
      "line": 0,
      "thread_id": "34996",
      "task_id": null,
      "user_id": null,
      "context": null,
      "exception": null
    },
    {
      "timestamp": "2025-09-02T02:10:42.168740",
      "level": "INFO",
      "message": "线程2日志36",
      "module": "thread_2",
      "function": "",
      "line": 0,
      "thread_id": "141444",
      "task_id": null,
      "user_id": null,
      "context": null,
      "exception": null
    },
    {
      "timestamp": "2025-09-02T02:10:42.168806",
      "level": "INFO",
      "message": "线程0日志38",
      "module": "thread_0",
      "function": "",
      "line": 0,
      "thread_id": "94620",
      "task_id": null,
      "user_id": null,
      "context": null,
      "exception": null
    },
    {
      "timestamp": "2025-09-02T02:10:42.168910",
      "level": "INFO",
      "message": "线程3日志36",
      "module": "thread_3",
      "function": "",
      "line": 0,
      "thread_id": "128036",
      "task_id": null,
      "user_id": null,
      "context": null,
      "exception": null
    },
    {
      "timestamp": "2025-09-02T02:10:42.168969",
      "level": "INFO",
      "message": "线程1日志39",
      "module": "thread_1",
      "function": "",
      "line": 0,
      "thread_id": "122196",
      "task_id": null,
      "user_id": null,
      "context": null,
      "exception": null
    },
    {
      "timestamp": "2025-09-02T02:10:42.169297",
      "level": "INFO",
      "message": "线程4日志40",
      "module": "thread_4",
      "function": "",
      "line": 0,
      "thread_id": "34996",
      "task_id": null,
      "user_id": null,
      "context": null,
      "exception": null
    },
    {
      "timestamp": "2025-09-02T02:10:42.169417",
      "level": "INFO",
      "message": "线程2日志37",
      "module": "thread_2",
      "function": "",
      "line": 0,
      "thread_id": "141444",
      "task_id": null,
      "user_id": null,
      "context": null,
      "exception": null
    },
    {
      "timestamp": "2025-09-02T02:10:42.169496",
      "level": "INFO",
      "message": "线程0日志39",
      "module": "thread_0",
      "function": "",
      "line": 0,
      "thread_id": "94620",
      "task_id": null,
      "user_id": null,
      "context": null,
      "exception": null
    },
    {
      "timestamp": "2025-09-02T02:10:42.169569",
      "level": "INFO",
      "message": "线程1日志40",
      "module": "thread_1",
      "function": "",
      "line": 0,
      "thread_id": "122196",
      "task_id": null,
      "user_id": null,
      "context": null,
      "exception": null
    },
    {
      "timestamp": "2025-09-02T02:10:42.169686",
      "level": "INFO",
      "message": "线程4日志41",
      "module": "thread_4",
      "function": "",
      "line": 0,
      "thread_id": "34996",
      "task_id": null,
      "user_id": null,
      "context": null,
      "exception": null
    },
    {
      "timestamp": "2025-09-02T02:10:42.169791",
      "level": "INFO",
      "message": "线程3日志37",
      "module": "thread_3",
      "function": "",
      "line": 0,
      "thread_id": "128036",
      "task_id": null,
      "user_id": null,
      "context": null,
      "exception": null
    },
    {
      "timestamp": "2025-09-02T02:10:42.170165",
      "level": "INFO",
      "message": "线程1日志41",
      "module": "thread_1",
      "function": "",
      "line": 0,
      "thread_id": "122196",
      "task_id": null,
      "user_id": null,
      "context": null,
      "exception": null
    },
    {
      "timestamp": "2025-09-02T02:10:42.170275",
      "level": "INFO",
      "message": "线程4日志42",
      "module": "thread_4",
      "function": "",
      "line": 0,
      "thread_id": "34996",
      "task_id": null,
      "user_id": null,
      "context": null,
      "exception": null
    },
    {
      "timestamp": "2025-09-02T02:10:42.170338",
      "level": "INFO",
      "message": "线程3日志38",
      "module": "thread_3",
      "function": "",
      "line": 0,
      "thread_id": "128036",
      "task_id": null,
      "user_id": null,
      "context": null,
      "exception": null
    },
    {
      "timestamp": "2025-09-02T02:10:42.170478",
      "level": "INFO",
      "message": "线程0日志40",
      "module": "thread_0",
      "function": "",
      "line": 0,
      "thread_id": "94620",
      "task_id": null,
      "user_id": null,
      "context": null,
      "exception": null
    },
    {
      "timestamp": "2025-09-02T02:10:42.170602",
      "level": "INFO",
      "message": "线程2日志38",
      "module": "thread_2",
      "function": "",
      "line": 0,
      "thread_id": "141444",
      "task_id": null,
      "user_id": null,
      "context": null,
      "exception": null
    },
    {
      "timestamp": "2025-09-02T02:10:42.170794",
      "level": "INFO",
      "message": "线程4日志43",
      "module": "thread_4",
      "function": "",
      "line": 0,
      "thread_id": "34996",
      "task_id": null,
      "user_id": null,
      "context": null,
      "exception": null
    },
    {
      "timestamp": "2025-09-02T02:10:42.170883",
      "level": "INFO",
      "message": "线程1日志42",
      "module": "thread_1",
      "function": "",
      "line": 0,
      "thread_id": "122196",
      "task_id": null,
      "user_id": null,
      "context": null,
      "exception": null
    },
    {
      "timestamp": "2025-09-02T02:10:42.171039",
      "level": "INFO",
      "message": "线程3日志39",
      "module": "thread_3",
      "function": "",
      "line": 0,
      "thread_id": "128036",
      "task_id": null,
      "user_id": null,
      "context": null,
      "exception": null
    },
    {
      "timestamp": "2025-09-02T02:10:42.171142",
      "level": "INFO",
      "message": "线程2日志39",
      "module": "thread_2",
      "function": "",
      "line": 0,
      "thread_id": "141444",
      "task_id": null,
      "user_id": null,
      "context": null,
      "exception": null
    },
    {
      "timestamp": "2025-09-02T02:10:42.171448",
      "level": "INFO",
      "message": "线程4日志44",
      "module": "thread_4",
      "function": "",
      "line": 0,
      "thread_id": "34996",
      "task_id": null,
      "user_id": null,
      "context": null,
      "exception": null
    },
    {
      "timestamp": "2025-09-02T02:10:42.171697",
      "level": "INFO",
      "message": "线程1日志43",
      "module": "thread_1",
      "function": "",
      "line": 0,
      "thread_id": "122196",
      "task_id": null,
      "user_id": null,
      "context": null,
      "exception": null
    },
    {
      "timestamp": "2025-09-02T02:10:42.171837",
      "level": "INFO",
      "message": "线程2日志40",
      "module": "thread_2",
      "function": "",
      "line": 0,
      "thread_id": "141444",
      "task_id": null,
      "user_id": null,
      "context": null,
      "exception": null
    },
    {
      "timestamp": "2025-09-02T02:10:42.171914",
      "level": "INFO",
      "message": "线程0日志41",
      "module": "thread_0",
      "function": "",
      "line": 0,
      "thread_id": "94620",
      "task_id": null,
      "user_id": null,
      "context": null,
      "exception": null
    },
    {
      "timestamp": "2025-09-02T02:10:42.171978",
      "level": "INFO",
      "message": "线程3日志40",
      "module": "thread_3",
      "function": "",
      "line": 0,
      "thread_id": "128036",
      "task_id": null,
      "user_id": null,
      "context": null,
      "exception": null
    },
    {
      "timestamp": "2025-09-02T02:10:42.172256",
      "level": "INFO",
      "message": "线程2日志41",
      "module": "thread_2",
      "function": "",
      "line": 0,
      "thread_id": "141444",
      "task_id": null,
      "user_id": null,
      "context": null,
      "exception": null
    },
    {
      "timestamp": "2025-09-02T02:10:42.172423",
      "level": "INFO",
      "message": "线程1日志44",
      "module": "thread_1",
      "function": "",
      "line": 0,
      "thread_id": "122196",
      "task_id": null,
      "user_id": null,
      "context": null,
      "exception": null
    },
    {
      "timestamp": "2025-09-02T02:10:42.172517",
      "level": "INFO",
      "message": "线程0日志42",
      "module": "thread_0",
      "function": "",
      "line": 0,
      "thread_id": "94620",
      "task_id": null,
      "user_id": null,
      "context": null,
      "exception": null
    },
    {
      "timestamp": "2025-09-02T02:10:42.172668",
      "level": "INFO",
      "message": "线程4日志45",
      "module": "thread_4",
      "function": "",
      "line": 0,
      "thread_id": "34996",
      "task_id": null,
      "user_id": null,
      "context": null,
      "exception": null
    },
    {
      "timestamp": "2025-09-02T02:10:42.172895",
      "level": "INFO",
      "message": "线程3日志41",
      "module": "thread_3",
      "function": "",
      "line": 0,
      "thread_id": "128036",
      "task_id": null,
      "user_id": null,
      "context": null,
      "exception": null
    },
    {
      "timestamp": "2025-09-02T02:10:42.172985",
      "level": "INFO",
      "message": "线程2日志42",
      "module": "thread_2",
      "function": "",
      "line": 0,
      "thread_id": "141444",
      "task_id": null,
      "user_id": null,
      "context": null,
      "exception": null
    },
    {
      "timestamp": "2025-09-02T02:10:42.173135",
      "level": "INFO",
      "message": "线程1日志45",
      "module": "thread_1",
      "function": "",
      "line": 0,
      "thread_id": "122196",
      "task_id": null,
      "user_id": null,
      "context": null,
      "exception": null
    },
    {
      "timestamp": "2025-09-02T02:10:42.173324",
      "level": "INFO",
      "message": "线程4日志46",
      "module": "thread_4",
      "function": "",
      "line": 0,
      "thread_id": "34996",
      "task_id": null,
      "user_id": null,
      "context": null,
      "exception": null
    },
    {
      "timestamp": "2025-09-02T02:10:42.173466",
      "level": "INFO",
      "message": "线程3日志42",
      "module": "thread_3",
      "function": "",
      "line": 0,
      "thread_id": "128036",
      "task_id": null,
      "user_id": null,
      "context": null,
      "exception": null
    },
    {
      "timestamp": "2025-09-02T02:10:42.173547",
      "level": "INFO",
      "message": "线程0日志43",
      "module": "thread_0",
      "function": "",
      "line": 0,
      "thread_id": "94620",
      "task_id": null,
      "user_id": null,
      "context": null,
      "exception": null
    },
    {
      "timestamp": "2025-09-02T02:10:42.173668",
      "level": "INFO",
      "message": "线程2日志43",
      "module": "thread_2",
      "function": "",
      "line": 0,
      "thread_id": "141444",
      "task_id": null,
      "user_id": null,
      "context": null,
      "exception": null
    },
    {
      "timestamp": "2025-09-02T02:10:42.173810",
      "level": "INFO",
      "message": "线程1日志46",
      "module": "thread_1",
      "function": "",
      "line": 0,
      "thread_id": "122196",
      "task_id": null,
      "user_id": null,
      "context": null,
      "exception": null
    },
    {
      "timestamp": "2025-09-02T02:10:42.174032",
      "level": "INFO",
      "message": "线程3日志43",
      "module": "thread_3",
      "function": "",
      "line": 0,
      "thread_id": "128036",
      "task_id": null,
      "user_id": null,
      "context": null,
      "exception": null
    },
    {
      "timestamp": "2025-09-02T02:10:42.174125",
      "level": "INFO",
      "message": "线程4日志47",
      "module": "thread_4",
      "function": "",
      "line": 0,
      "thread_id": "34996",
      "task_id": null,
      "user_id": null,
      "context": null,
      "exception": null
    },
    {
      "timestamp": "2025-09-02T02:10:42.174354",
      "level": "INFO",
      "message": "线程0日志44",
      "module": "thread_0",
      "function": "",
      "line": 0,
      "thread_id": "94620",
      "task_id": null,
      "user_id": null,
      "context": null,
      "exception": null
    },
    {
      "timestamp": "2025-09-02T02:10:42.174573",
      "level": "INFO",
      "message": "线程1日志47",
      "module": "thread_1",
      "function": "",
      "line": 0,
      "thread_id": "122196",
      "task_id": null,
      "user_id": null,
      "context": null,
      "exception": null
    },
    {
      "timestamp": "2025-09-02T02:10:42.174797",
      "level": "INFO",
      "message": "线程3日志44",
      "module": "thread_3",
      "function": "",
      "line": 0,
      "thread_id": "128036",
      "task_id": null,
      "user_id": null,
      "context": null,
      "exception": null
    },
    {
      "timestamp": "2025-09-02T02:10:42.174913",
      "level": "INFO",
      "message": "线程2日志44",
      "module": "thread_2",
      "function": "",
      "line": 0,
      "thread_id": "141444",
      "task_id": null,
      "user_id": null,
      "context": null,
      "exception": null
    },
    {
      "timestamp": "2025-09-02T02:10:42.175127",
      "level": "INFO",
      "message": "线程0日志45",
      "module": "thread_0",
      "function": "",
      "line": 0,
      "thread_id": "94620",
      "task_id": null,
      "user_id": null,
      "context": null,
      "exception": null
    },
    {
      "timestamp": "2025-09-02T02:10:42.175335",
      "level": "INFO",
      "message": "线程1日志48",
      "module": "thread_1",
      "function": "",
      "line": 0,
      "thread_id": "122196",
      "task_id": null,
      "user_id": null,
      "context": null,
      "exception": null
    },
    {
      "timestamp": "2025-09-02T02:10:42.175508",
      "level": "INFO",
      "message": "线程4日志48",
      "module": "thread_4",
      "function": "",
      "line": 0,
      "thread_id": "34996",
      "task_id": null,
      "user_id": null,
      "context": null,
      "exception": null
    },
    {
      "timestamp": "2025-09-02T02:10:42.175688",
      "level": "INFO",
      "message": "线程3日志45",
      "module": "thread_3",
      "function": "",
      "line": 0,
      "thread_id": "128036",
      "task_id": null,
      "user_id": null,
      "context": null,
      "exception": null
    },
    {
      "timestamp": "2025-09-02T02:10:42.176061",
      "level": "INFO",
      "message": "线程2日志45",
      "module": "thread_2",
      "function": "",
      "line": 0,
      "thread_id": "141444",
      "task_id": null,
      "user_id": null,
      "context": null,
      "exception": null
    },
    {
      "timestamp": "2025-09-02T02:10:42.176148",
      "level": "INFO",
      "message": "线程0日志46",
      "module": "thread_0",
      "function": "",
      "line": 0,
      "thread_id": "94620",
      "task_id": null,
      "user_id": null,
      "context": null,
      "exception": null
    },
    {
      "timestamp": "2025-09-02T02:10:42.176341",
      "level": "INFO",
      "message": "线程1日志49",
      "module": "thread_1",
      "function": "",
      "line": 0,
      "thread_id": "122196",
      "task_id": null,
      "user_id": null,
      "context": null,
      "exception": null
    },
    {
      "timestamp": "2025-09-02T02:10:42.176452",
      "level": "INFO",
      "message": "线程4日志49",
      "module": "thread_4",
      "function": "",
      "line": 0,
      "thread_id": "34996",
      "task_id": null,
      "user_id": null,
      "context": null,
      "exception": null
    },
    {
      "timestamp": "2025-09-02T02:10:42.176702",
      "level": "INFO",
      "message": "线程3日志46",
      "module": "thread_3",
      "function": "",
      "line": 0,
      "thread_id": "128036",
      "task_id": null,
      "user_id": null,
      "context": null,
      "exception": null
    },
    {
      "timestamp": "2025-09-02T02:10:42.176910",
      "level": "INFO",
      "message": "线程2日志46",
      "module": "thread_2",
      "function": "",
      "line": 0,
      "thread_id": "141444",
      "task_id": null,
      "user_id": null,
      "context": null,
      "exception": null
    },
    {
      "timestamp": "2025-09-02T02:10:42.177052",
      "level": "INFO",
      "message": "线程0日志47",
      "module": "thread_0",
      "function": "",
      "line": 0,
      "thread_id": "94620",
      "task_id": null,
      "user_id": null,
      "context": null,
      "exception": null
    },
    {
      "timestamp": "2025-09-02T02:10:42.177210",
      "level": "INFO",
      "message": "线程3日志47",
      "module": "thread_3",
      "function": "",
      "line": 0,
      "thread_id": "128036",
      "task_id": null,
      "user_id": null,
      "context": null,
      "exception": null
    },
    {
      "timestamp": "2025-09-02T02:10:42.177601",
      "level": "INFO",
      "message": "线程2日志47",
      "module": "thread_2",
      "function": "",
      "line": 0,
      "thread_id": "141444",
      "task_id": null,
      "user_id": null,
      "context": null,
      "exception": null
    },
    {
      "timestamp": "2025-09-02T02:10:42.177666",
      "level": "INFO",
      "message": "线程3日志48",
      "module": "thread_3",
      "function": "",
      "line": 0,
      "thread_id": "128036",
      "task_id": null,
      "user_id": null,
      "context": null,
      "exception": null
    },
    {
      "timestamp": "2025-09-02T02:10:42.177825",
      "level": "INFO",
      "message": "线程0日志48",
      "module": "thread_0",
      "function": "",
      "line": 0,
      "thread_id": "94620",
      "task_id": null,
      "user_id": null,
      "context": null,
      "exception": null
    },
    {
      "timestamp": "2025-09-02T02:10:42.177941",
      "level": "INFO",
      "message": "线程2日志48",
      "module": "thread_2",
      "function": "",
      "line": 0,
      "thread_id": "141444",
      "task_id": null,
      "user_id": null,
      "context": null,
      "exception": null
    },
    {
      "timestamp": "2025-09-02T02:10:42.178136",
      "level": "INFO",
      "message": "线程3日志49",
      "module": "thread_3",
      "function": "",
      "line": 0,
      "thread_id": "128036",
      "task_id": null,
      "user_id": null,
      "context": null,
      "exception": null
    },
    {
      "timestamp": "2025-09-02T02:10:42.178250",
      "level": "INFO",
      "message": "线程2日志49",
      "module": "thread_2",
      "function": "",
      "line": 0,
      "thread_id": "141444",
      "task_id": null,
      "user_id": null,
      "context": null,
      "exception": null
    },
    {
      "timestamp": "2025-09-02T02:10:42.178360",
      "level": "INFO",
      "message": "线程0日志49",
      "module": "thread_0",
      "function": "",
      "line": 0,
      "thread_id": "94620",
      "task_id": null,
      "user_id": null,
      "context": null,
      "exception": null
    }
  ]
}